[{"u":"ددلانا","d":"ददलाना","r":"dadlānā, dut, dat, dutānā, datnā, ḍāṅṭnā","src":"Hindi","ety":"fr. dut or dat; cf. dutānā; datnā, and ḍāṅṭnā","pos":"v.t.","def":"v.t. To rebuke, to chide, to snub.","pg":508,"fq":0},{"u":"ددوڙا","d":"ददोड़ा","r":"dadoṛā, dadauṛā","src":"Hindi","ety":"dād, q.v.+Prk. अअडओ = S. अ+र+कः","pos":"s.m.","def":"s.m. A bump or swelling (caused by the bite of an insect, or by bad state of the blood).","pg":508,"chain":[["Prakrit","अअडओ"],["Sanskrit","अ"]],"fq":0},{"u":"ڐڐورا","d":"डडोरा","r":"ḍaḍorā, ḍhanḍhorā","src":"Hindi","ety":"","pos":"","def":"s.m. corr. of ḍhanḍhorā, q.v.","pg":564,"qv":["ḍhanḍhorā"],"reg":["corrupted form"],"fq":0},{"u":"دادرا","d":"दादरा","r":"dādrā","src":"Hindi","ety":"dādur, q.v.+ā = Prk. अओ = S. अ+कः","pos":"s.m.","def":"s.m. A kind of song to a quick air (so called from its resemblance to the quick tones of a frog: this class of songs is most common in Agra and Bundelkhand); — the palate, the uvula.","pg":500,"chain":[["Prakrit","अओ"],["Sanskrit","अ"]],"fq":0},{"u":"ددري","d":"दद्री","r":"dadrī","src":"Hindi","ety":"prob. fr. S. दृ, by redupl.","pos":"s.f.","def":"s.f. Unripe corn (chiefly barley) which is cut from time to time and brought home to be eaten without being taken to the threshing-floor.","pg":508,"chain":[["Sanskrit","दृ"]],"fq":0},{"u":"ددرو","d":"दद्रु","r":"dadru, dadrū","src":"Sanskrit","ety":"","pos":"s.f.","def":"s.f. A cutaneous eruption or rash, herpes, &c. (see dād)","pg":508,"subs":[["dadru-rogin or rogī","adj. & s.m. Herpetic; — a person having herpes.",0]],"fq":0},{"u":"دادسسرا","d":"दादसुसरा","r":"dādsusrā, dādasrā","src":"Hindi","ety":"S. तात+श्वशुरकः","pos":"s.m.","def":"s.m. Father-in-law of a wife's or husband's father-in-law.","pg":500,"chain":[["Sanskrit","तात"]],"fq":0},{"u":"دادو","d":"दादू","r":"dādū, dādā","src":"Hindi","ety":"see dādā","pos":"s.m.","def":"s.m. Name of a famous faqīr","pg":500,"subs":[["dādū-panthī","s.m. Name of the sect who are followers of the faqīr Dādū; a member of that sect.",0]],"fq":0,"ipa":"/d̪ɑː.d̪oː/","wety":"Named after Syed Dad Muhammad Shah Alias Dadu, the founder of the city."},{"u":"دڐوکنا","d":"दडूकना","r":"daḍūknā","src":"Hindi","ety":"redupl. of ḍoṅknā","pos":"v.n.","def":"v.n. To low, to bellow (as cattle; = ḍakārne, q.v.); to roar; to thunder.","pg":508,"qv":["ḍakārne"],"fq":0},{"u":"دادر","d":"दादुर","r":"dādur","src":"Hindi","ety":"Prk. दद्दुरो; S. दर्दुरः","pos":"s.m.","def":"s.m. A frog.","pg":500,"chain":[["Prakrit","दद्दुरो"],["Sanskrit","दर्दुरः"]],"fq":0},{"u":"دادروا","d":"दादुरवा","r":"dādurwā","src":"Hindi","ety":"˚wā = Prk. अओ (with w inserted) = S. क+कः","pos":"s.m.","def":"s.m. = dādur, q.v.","pg":500,"qv":["dādur"],"chain":[["Prakrit","अओ"],["Sanskrit","क"]],"fq":0},{"u":"دايجا","d":"दायजा","r":"dāʼejā, dāʼijā","src":"Hindi","ety":"S. दाय+आद्य+कं","pos":"s.m.","def":"s.m. Dowry, dower, portion, nuptial present, marriage-gift ( = dahez).","pg":505,"chain":[["Sanskrit","दाय"]],"fq":0},{"u":"دائين","d":"दायं","r":"dāʼeṅ","src":"Hindi","ety":"S. दाम+इका; or fr. dāwan, q.v.","pos":"s.f.","def":"s.f. Tying a number of bullocks together for the purpose of treading out grain from the ear; treading out grain by means of a number of bullocks tied together (c.f. dāwan); — untnreshed corn.","pg":505,"chain":[["Sanskrit","दाम"]],"fq":0},{"u":"دائين","d":"दायं","r":"dāʼeṅ","src":"Hindi","ety":"prob. onomat.","pos":"s.f.","def":"s.f. Booming sound (of guns, &c.): — dāʼeṅ-dāʼeṅ s.f. Idem.","pg":505,"fq":0},{"u":"دائين","d":"दायं","r":"dāʼeṅ, dahine, dahinā","src":"Hindi","ety":"i.q. dahine, obl. of dahinā, q.v.","pos":"adv.","def":"adv. To the right, on the right (hand or side)","pg":505,"subs":[["dāʼeṅ-bāʼeṅ","adv. Right and left",0],["dāʼeṅ-bāʼeṅ de-kar nikal-jānā","To dodge right and left and get away",1],["dāʼen-bāʼeṅ dekhnā","To look right and left, to keep a sharp look out, to be vigilant or careful",1],["dāʼeṅ-bāʼeṅ karnā","v.t. 'To put to the right and left'; to put out of the way, to stow away, secrete, conceal.",1]],"fq":0},{"u":"ڐف","d":"डफ","r":"ḍaf","src":"Hindi","ety":"","pos":"s.m.","def":"s.m. = ḍaph, daf, q.v.","pg":565,"qv":["daf"],"fq":1},{"u":"دفع","d":"","r":"dafʻ, dafʻa","src":"Arabic","ety":"inf. n. of دفع 'to push, to repel,' &c.","pos":"s.m.","def":"s.m. Pushing, thrusting, beating off; preventing, averting, repelling, repulsion; warding off, preparing","pg":519,"subs":[["dafʻuʼl-waqt","s.m. Putting off, postponement",0],["dafʻ karnā","v.t. To push or thrust away or off, to dispel, remove, repel, avert, ward off, parry; to guard (oneself, against, -se)",1],["dafʻ honā","v.n. To be beaten off, be repelled, &c.; to be turned back; to return.",1]],"fq":1,"sh":4943},{"u":"دف","d":"","r":"daf, daffuṉ","src":"Persian","ety":"for A. daffuṉ","pos":"s.m.","def":"s.m. A kind of bass tambourine (without cymbals); a tambourine.","pg":519,"chain":[["Arabic","daffu"]],"fq":1},{"u":"دف","d":"","r":"daf, dafʼuṉ","src":"Hindi","ety":"prob. fr. A. dafʼuṉ, v.n. fr. rt. دفأ","pos":"s.m.","def":"s.m. Heat, warmth; ebullition; overflow, excess; disagreeableness, noxious property","pg":519,"subs":[["daf marnā","(-kā), Disagreeableness (of a thing) to be removed, noxious property to be extracted or destroyed.",0]],"root":"د ف أ","chain":[["Arabic","daf"]],"fq":1},{"u":"دفعه","d":"","r":"dafʻa, dafʻat","src":"Persian","ety":"for A. دفعة dafʻat, inf. n. of un. fr. دفع 'to push,' &c.","pos":"s.f.","def":"s.f. One time, one turn or bout; time; a moment; — a collective body; a class; an item, a section","pg":519,"subs":[["dafʻa-ba-dafʻa","adv. From time to time, time after time, repeatedly",0],["dafʻa-dār","vulg. dafʻe-dar, s.m. An officer commanding a small body of cavalry or infantry",0],["kaʼī dafʻa","adv. Several times, repeatedly.",0]],"root":"د ف ع","chain":[["Arabic","دفعة"]],"fq":1},{"u":"دفعدار","d":"","r":"dafʻa-dār","src":"Sanskrit","ety":"","pos":"s.m.","def":"s.m. See s.v. dafʻa.","pg":519,"fq":0},{"u":"دفائن","d":"","r":"dafāʼin, dafīna","src":"Arabic","ety":"","pos":"","def":"s.m. pl. (of dafīna), Buried or hidden things, or treasures.","pg":519,"fq":0},{"u":"ڐفالچي","d":"","r":"ḍafālćī, ḍafālī","src":"Hindi","ety":"","pos":"s.m.","def":"s.m. = dafālī, q.v.","pg":565,"qv":["dafālī"],"fq":0},{"u":"دفالي","d":"","r":"dafālī","src":"Hindi","ety":"daf, q.v.+Prk. आलिओ = S. आल+इकः (इन्+कः)","pos":"s.m.","def":"s.m. A man of the class whose business is playing the tambourine; a kind of faqīr who always plays upon the daf or tambourine; a tambourine player (vulg. ḍafālī, ḍapālī).","pg":519,"reg":["common speech"],"chain":[["Prakrit","आलिओ"],["Sanskrit","आल"]],"fq":1},{"u":"ڐفالی","d":"","r":"ḍafālī, ḍafālćī","src":"Hindi","ety":"","pos":"s.m.","def":"s.m. = dafālī, q.v.","pg":565,"qv":["dafālī"],"fq":1},{"u":"دفرقليا","d":"","r":"dafar-qaliyā, dafar-qalya","src":"Hindi","ety":"A. دفر+قلية, inf. n. of un. fr. دفرقليه 'to cook,' &c.","pos":"s.m.","def":"s.m. An abominable mess, tasteless victnals, a dish in which much broth, vegetables, &c. are mixed to make it go further, wishwash.","pg":519,"root":"د ف ر ق ل ي","chain":[["Arabic","دفر"]],"fq":0},{"u":"دفرقليه","d":"","r":"dafar-qalya, dafar-qaliyā","src":"Persian","ety":"A. دفر+قلية, inf. n. of un. fr. دفرقليه 'to cook,' &c.","pos":"s.m.","def":"s.m. An abominable mess, tasteless victnals, a dish in which much broth, vegetables, &c. are mixed to make it go further, wishwash.","pg":519,"root":"د ف ر ق ل ي","chain":[["Arabic","دفر"]],"fq":0},{"u":"دفعات","d":"","r":"dafʻāt, dafʻa","src":"Arabic","ety":"","pos":"","def":"s.m. pl. (of dafʻa), Times, &c. (see dafʻa).","pg":519,"fq":0},{"u":"دفعتًا","d":"","r":"dafʻataṉ, dafʻatā","src":"Persian","ety":"for A. دفعةً, acc. of دفعة","pos":"adv.","def":"adv. Time after time, often; — at one time, all at once, suddenly.","pg":519,"chain":[["Arabic","دفعةً"]],"fq":0,"sh":2252},{"u":"دفاتر","d":"","r":"dafātir, daftar","src":"Arabic","ety":"","pos":"","def":"s.m. pl. (of daftar), Books; registers; volumes, &c.","pg":519,"fq":0},{"u":"دافع","d":"","r":"dāfěʻ, dāfěʻa","src":"Arabic","ety":"act. part. n. of دفع to repel,' &c.","pos":"adj.&s.m.","def":"adj. & s.m. Repelling, repellent; — repeller, &c.","pg":501,"subs":[["quwwat-ě-dāfiʻa","s.f. Repelling power; power of expulsion.",0]],"fq":0},{"u":"دافعه","d":"","r":"dāfěʻa, dāfěʻ","src":"Persian","ety":"for A. دافعة, fem. of dāfěʻ","pos":"adj.&s.m.","def":"adj. & s.m. Repelling, repellent; — repeller, &c.","pg":501,"subs":[["quwwat-ě-dāfiʻa","s.f. Repelling power; power of expulsion.",0]],"chain":[["Arabic","دافعة"]],"fq":0},{"u":"دفينه","d":"","r":"dafīna, dafīnat","src":"Persian","ety":"for A. دفينة dafīnat, fr. دفين, rt. دفن 'to bury'","pos":"s.m.","def":"s.m. A thing buried; buried or hidden treasure; treasure-trove.","pg":519,"root":"د ف ي ن","chain":[["Arabic","دفينة"]],"fq":0},{"u":"دفعيه","d":"","r":"dafʻīya","src":"Hindi","ety":"formed, after the model of the A., fr. دفع","pos":"s.m.","def":"s.m. Repulsion, averting, preventing, prevention, warding off; a preventive","pg":519,"subs":[["dafʻīya karnā","(-kā), To repel, &c.",1]],"root":"د ف ع","fq":0},{"u":"دفله","d":"","r":"dafla","src":"Hindi","ety":"daf, q.v.+Prk. अडओ = S. ल+कः","pos":"s.m.","def":"s.m. A small tambourine.","pg":519,"chain":[["Prakrit","अडओ"],["Sanskrit","ल"]],"fq":0},{"u":"ڐفلا","d":"डफला","r":"ḍaflā, ḍaflī","src":"Hindi","ety":"","pos":"s.f.","def":"s.f. (dim.) = ḍaphlā, q.v.","pg":565,"qv":["ḍaphlā"],"fq":0},{"u":"ڐفلي","d":"डफली","r":"ḍaflī","src":"Hindi","ety":"","pos":"s.f.","def":"s.f. (dim.) = H ڐفلا डफला ḍaflā, s.m. = ḍaphlā, q.v.","pg":565,"qv":["ḍaphlā"],"fq":0},{"u":"دفن","d":"","r":"dafn, dafan","src":"Arabic","ety":"inf. n. of دفن 'to bury'","pos":"s.m.","def":"s.m. Burying, burial, interment; covering, hiding, concealing — dafn karnā, v.t. To bury; to hide, conceal","pg":519,"subs":[["dafn honā","v.n. To be buried.",1]],"fq":0,"sh":1274,"ipa":"/d̪əfn/","der":["بَعْدِ دَفْن","دَفْن رَہْنا","دَفْن کَرْنا","دَفْن کَفَن","دَفْن ہونا","دَفْنانا"],"wety":"Borrowed from Classical Persian دفن (dafn), from Arabic دَفْن (dafn)."},{"u":"دفنانا","d":"","r":"dafnānā","src":"Hindi","ety":"dafn, q.v.+ā = āw = Prk. āwe = S. āpi (caus. aug.)+nā","pos":"v.t.","def":"v.t. To bury, &c. ( = dafn karnā).","pg":519,"chain":[["Prakrit","āwe"],["Sanskrit","āpi"]],"fq":0,"ipa":"/d̪əf.nɑː.nɑː/","wety":"From دَفْن (dafn) + ـَانا (-ānā) by analogy with Classical Persian دَفْن کَرْدَن (dafn kardan). Compare Gujarati દફનાવવું (daphnāvvũ)."},{"u":"دفتر","d":"","r":"daftar, diftar","src":"Persian","ety":"A. daftar, diftar, fr. the P.; Gr. διφθερα 'a skin,' &c.","pos":"s.m.","def":"s.m. A roll, scroll, list; an index; a bundle of papers or written documents tied together in a cloth; a record, register, journal, book, volume, account-book; an official statement or report (especially of public revenue); archives; a record-office; an office, counting-house, place of business","pg":519,"subs":[["daftar-ḵẖāna","s.m. Record-office; office, counting-house; archives",0],["daftar-ḵẖarć","s.m. Office-charges",0],["daftar-navīs","s.m. A clerk; a registrar",0],["sar-ě-daftar","s.m. Head of an office; head clerk.",0]],"chain":[["Arabic","daftar"]],"fq":1,"sh":396,"ipa":"/d̪əf.t̪əɾ/","wety":"Borrowed from Classical Persian دَفْتَر (daftar)."},{"u":"دفتري","d":"","r":"daftarī","src":"Persian","ety":"daftar, q.v.+Zend aêna = S. इन्","pos":"s.m.","def":"s.m. An office-keeper; a man who has charge of the stationery, &c. of an office, and whose business it is to arrange and bind the papers and books, rule sheets of paper, make and mend pens, prepare envelopes, &c.","pg":519,"chain":[["Sanskrit","इन्"]],"fq":0},{"u":"دفتي","d":"","r":"daftī, daftīn","src":"Persian","ety":"","pos":"s.f.","def":"s.f. The sides or boards (of the binding of a book); pasteboard.","pg":519,"fq":0},{"u":"دفتين","d":"","r":"daftīn, daftī","src":"Persian","ety":"","pos":"s.f.","def":"s.f. The sides or boards (of the binding of a book); pasteboard.","pg":519,"fq":0},{"u":"داغ","d":"","r":"dāg̠","src":"Persian","ety":"Zend dagha, fr. daz; S. दाह, rt. दह्, orig. दघ्; Prk. दाघ","pos":"s.m.","def":"s.m. A mark burnt in, a brand, cautery; mark, spot, speck; stain; stigma; blemish; iron-mould; freckle; pock; scar, cicatrix; wound, sore; grief, sorrow; misfortune, calamity; loss, injury, damage; — (adjectively) branded, cauterized, scarred, wounded, &c.","pg":501,"subs":[["dāg̠ bar bālāʼě dāg̠ = dāg̠-par dāg̠","q.v.",0],["dāg̠-bel","s.f. Marking out the lines of a road with a spade; a line of road; mark",0],["dāg̠-par dāg̠","One misfortune following another, calamity on calamity",0],["dāg̠ ćaṛhānā = dāg̠ lagānā","q.v.",1],["dāg̠-dār","adj. Burnt; branded, cauterized; scarred; marked, spotted; streaked, striped; stained; blemished, spoiled",0],["dāg̠ dilānā","(-meṅ), To set fire (to), to set alight (as a pyre, &c.)",1],["dāg̠ denā","(-meṅ), To mark, to scar; to wound, to grieve",1],["dāg̠-karnewālā","adj. (f. -ī), Corrosive, caustic",0],["dāg̠ khānā","(-se), To be wounded, or grieved, &c. (by)",1],["dāg̠ lānā","(-meṅ), To vilify, &c. = dāg̠ lagānā (-meṅ), To stain, sully, vilify, defame",1],["dāg̠ lagnā","(meṅ), To be burnt; to be branded; to be defamed, to get a bad name; to be damaged",1],["dāg̠ honā","v.n. To be cauterized, be scarred, &c.",1]],"chain":[["Sanskrit","दाह"],["Prakrit","दाघ"]],"fq":2,"sh":2169,"ipa":"/d̪ɑːɣ/","wety":"Borrowed from Classical Persian داغ (dāġ)."},{"u":"داگ","d":"दाग","r":"dāg, dāgnā, dāg̠, dāg̠nā","src":"Hindi","ety":"","pos":"","def":"s.m. = H داگنا दागना dāgnā, v.t. corr. of dāg̠; and dāg̠nā, qq.v.","pg":501,"reg":["corrupted form"],"fq":2},{"u":"ڐگ","d":"डग","r":"ḍag, ḍig, ḍignā","src":"Hindi","ety":"see ḍignā","pos":"s.f.","def":"s.f. Pace, step, stride (also written ḍheṅg, deg)","pg":565,"subs":[["ḍag bharnā","ḍag dharnā, v.n. To step, step out, stride.",1]],"fq":2},{"u":"دغا","d":"","r":"dag̠ā, dag̠l, dag̠dag̠a","src":"Persian","ety":"prob. connected with dag̠l and dag̠dag̠a","pos":"s.f.","def":"s.f. Deceit, imposture, treachery; cheat, fraud, artifice, delusion","pg":519,"subs":[["dagā-bāz","adj. & s.m. Deceitful, treacherous, fraudulent; — cheat, knave, impostor, traitor",0],["dagā-bāzī","s.f. Deceitfulness, fraud, imposture, cheating, knavery, treachery, foul play, villainy",0],["dag̠ā-ḵẖorī","s.f. The being deceived or imposed on; — deceit, treachery",0],["dag̠ā-dār","adj. & s.m. = dag̠ā-bāz",0],["dag̠ā-dārī","s.f. = dag̠ā-bāzī",0],["dag̠ā denā","(-ko), To deceive, impose on, cheat",1],["dag̠ā karnā","(-se, or ke sāth), To act deceitfully or treacherously, to practise deceit or treachery, to play false, &c.",1],["dag̠ā khānā","(-se), To be deceived or imposed on (by).",1]],"fq":1,"sh":1182,"ipa":"/d̪ə.ɣɑː/","wety":"Borrowed from Classical Persian دغا (daġā)."},{"u":"دگدهنا","d":"दगधना","r":"dagadhnā","src":"Hindi","ety":"dagadh˚ = S. दग्ध, p.p.p. of rt. दह्","pos":"v.t.","def":"v.t. To burn, scorch, singe; to hurt, wound; to tease, vex, torment, pester; to chide, upbraid, threaten; to revile.","pg":522,"chain":[["Sanskrit","दग्ध"]],"fq":0},{"u":"دغائي","d":"दग़ाई","r":"dag̠āʼī","src":"Hindi","ety":"dag̠ā(nā)+āʼī = Prk. एअव्वअइआ = S. (इ)तव्य+क+इका","pos":"s.f.","def":"s.f. Pri e paid for branding or marking.","pg":519,"chain":[["Prakrit","एअव्वअइआ"]],"fq":0},{"u":"دغل","d":"","r":"dag̠al","src":"Arabic","ety":"v.n. fr. دغل; used in P. with amplification of signification","pos":"s.m.","def":"s.m. Corrupt state, corruptness, unsoundness; corruption, vice, depravity; deceit, fraud, treachery, villainy ( = dag̠ā); base coin; — a cheat, impostor, villain; a pickpocket; confusedness or entanglement of plants or herbage; abundance or luxuriance of herbage; luxuriant, tangled, or dense herbage; — adj. Unsound; base (as coin); corrupt, depraved; false, insincere, deceitful, treacherous","pg":519,"subs":[["dag̠al-bāz","adj. = dag̠ā-bāz, q.v.s.v. dag̠ā",0],["dag̠al-faṣal","s.f. Depravity; duplicity, deceit, treachery.",0]],"root":"د غ ل","chain":[["Persian","with"]],"fq":0,"sh":1164},{"u":"دغلی","d":"","r":"dag̠alī, dag̠lī, dag̠al","src":"Persian","ety":"fr. dag̠al","pos":"adj.","def":"adj. Deceitful, treacherous; — dag̠alī or dag̠lī, s.f. Deceit, fraud, treachery, villainy ( = dag̠al).","pg":519,"fq":0},{"u":"ڐگن","d":"डगण","r":"ḍagan","src":"Hindi","ety":"","pos":"s.m.","def":"s.m. A combination of four short syllables.","pg":566,"fq":0},{"u":"دغانا","d":"ददग़ाना","r":"dag̠ānā, dāg̠nā","src":"Hindi","ety":"caus. of dāg̠nā","pos":"v.t.","def":"v.t. To cause to be, or to have, branded or marked; — to cause (a gun) to be fired.","pg":519,"fq":0},{"u":"دگڙ","d":"दगड़","r":"dagaṛ","src":"Hindi","ety":"S. द्रकटः, or द्रगडः","pos":"s.m.","def":"s.m. A kettle-drum (cf. ḍaṅkā and ḍhakkā).","pg":522,"chain":[["Sanskrit","द्रकटः"]],"fq":1},{"u":"ڐگر","d":"डगर","r":"ḍagar, ḍagrā, ḍag, ḍagar batānā, ko, aur ḍagar ćalnā","src":"Hindi","ety":"","pos":"","def":"s.f. = H ڐگرا डगरा ḍagrā, s.m. (fr. ḍag, q.v.), Highway, way, road, path, track; a wide path between fields (for the passage of cattle, &c.)","pg":566,"subs":[["ḍagar batānā","(-ko), To show or point out the road, to direct, to guide",1],["aur ḍagar ćalnā","'To take another road or path'; to mislead, deceive, trick, cheat.",0]],"qv":["ḍag"],"fq":1},{"u":"دگڙنا","d":"दगड़ना","r":"dagaṛnā","src":"Hindi","ety":"","pos":"v.n.","def":"v.n. To rock; to roll, &c. ( = ḍagarnā, q.v.); — v.t. To doubt, discredit, disbelieve (a true testimony, &c.).","pg":522,"qv":["ḍagarnā"],"fq":0},{"u":"ڐگرنا","d":"डगरना","r":"ḍagarnā","src":"Hindi","ety":"","pos":"s.m.","def":"s.m. (local), A pole on which a load is suspended.","pg":566,"fq":0},{"u":"ڐگرنا","d":"डगरना","r":"ḍagarnā, ḍigarnā, ḍagar, ḍag","src":"Hindi","ety":"see ḍagar; and ḍag","pos":"v.n.","def":"v.n. To go or walk along a road, to travel, to roam; to go away, take one's departure, be off; to roll; to totter","pg":566,"subs":[["ḍigar-jānā","v.n. To go away, &c. ( = ḍigarnā)",1],["ḍagar-ḍagar karnā","v.n. To totter along, to walk with tottering steps; to roll.",1]],"fq":0},{"u":"ڐگڐگ","d":"डगडग","r":"ḍag-ḍag, ḍag, ḍignā","src":"Hindi","ety":"by redupl. of ḍag; see ḍignā","pos":"adj.&s.m.","def":"adj. & s.m. Shaking, tottering, trembling, &c. ( = ḍag-mag; and ḍagmagāhaṭ, qq.v.).","pg":565,"fq":0},{"u":"دگدگا","d":"दगदगा","r":"dagdagā","src":"Hindi","ety":"S. दघ्, for दह्, by redupl.+कः","pos":"adj.","def":"adj. (f. -ī), Burning, shining, bright; — s.m. A burning lamp (placed within a paper cup).","pg":522,"chain":[["Sanskrit","दघ्"]],"fq":0},{"u":"دغدغا","d":"","r":"dag̠dag̠ā, dag̠dag̠a","src":"Hindi","ety":"fr. A. دغدغة dag̠dag̠at, inf. n. f. of دغدغ 'to tickle,' &c.; used in P. with amplification of signification","pos":"s.m.","def":"s.m. 'Titillation'; inclination or prompting (of the mind); suspicion, doubt, distrust; mental disturbance, tumult, perturbation, perplexity, anxiety, solicitude, care; alarm, fear, dread, trepidation, awe.","pg":519,"chain":[["Arabic","دغدغة"],["Persian","with"]],"fq":0},{"u":"دغدغه","d":"","r":"dag̠dag̠a, dag̠dag̠ā","src":"Persian","ety":"fr. A. دغدغة dag̠dag̠at, inf. n. f. of دغدغ 'to tickle,' &c.; used in P. with amplification of signification","pos":"s.m.","def":"s.m. 'Titillation'; inclination or prompting (of the mind); suspicion, doubt, distrust; mental disturbance, tumult, perturbation, perplexity, anxiety, solicitude, care; alarm, fear, dread, trepidation, awe.","pg":519,"chain":[["Arabic","دغدغة"],["Persian","with"]],"fq":0},{"u":"دگدگاهٿ","d":"दगदगाहट","r":"dagdagāhaṭ","src":"Hindi","ety":"dagdagā(nā)+āhaṭ = āwaṭ = Prk. एअव्वअट्टं = S. (इ)तव्य+क+त्वं","pos":"s.f.","def":"s.f. Brilliance, splendour; sparkling, sparkle, glow, twinkling, twinkle (as of a star).","pg":522,"chain":[["Prakrit","एअव्वअट्टं"]],"fq":0},{"u":"ڐگڐگاکر","d":"डगडगाकर","r":"ḍagḍagākar, ḍagḍagāke, ḍagḍagānā, ḍakdakākar, dakdakānā","src":"Hindi","ety":"","pos":"","def":"= H ڐگڐگاکے डगडगाके ḍagḍagāke, = H ڐگدگانا डगडगाना ḍagḍagānā, See ḍakdakākar, and dakdakānā.","pg":565,"fq":0},{"u":"ڐگڐگاکے","d":"डगडगाके","r":"ḍagḍagāke, ḍagḍagākar, ḍagḍagānā, ḍakdakākar, dakdakānā","src":"Hindi","ety":"","pos":"","def":"= H ڐگڐگاکر डगडगाकर ḍagḍagākar, = H ڐگدگانا डगडगाना ḍagḍagānā, See ḍakdakākar, and dakdakānā.","pg":565,"fq":0},{"u":"دگدگانا","d":"दगदगाना","r":"dagdagānā","src":"Hindi","ety":"dagdag˚ = S. दह् (or दघ्), redupl.+ā = āw = Prk. आवे = S. आपि caus. augment","pos":"v.n.","def":"v.n. To burn brightly, to shine, glow, gleam, twinkle; — to be inflamed, be very red.","pg":522,"chain":[["Sanskrit","दह्"],["Prakrit","आवे"],["Sanskrit","आपि"]],"fq":0},{"u":"ڐگڐگانا","d":"डगडगाना","r":"ḍagḍagānā, ḍagḍag","src":"Hindi","ety":"see ḍagḍag","pos":"v.n.","def":"v.n. To shake, totter, &c. ( = ḍagmagānā, q.v.).","pg":566,"qv":["ḍagmagānā"],"fq":0},{"u":"ڐگدگانا","d":"डगडगाना","r":"ḍagḍagānā, ḍagḍagākar, ḍagḍagāke, ḍakdakākar, dakdakānā","src":"Hindi","ety":"","pos":"","def":"= H ڐگڐگاکر डगडगाकर ḍagḍagākar, = H ڐگڐگاکے डगडगाके ḍagḍagāke, See ḍakdakākar, and dakdakānā.","pg":565,"fq":0},{"u":"ڐگڐگانا","d":"डगडगाना","r":"ḍagḍagānā, ḍugḍugānā","src":"Hindi","ety":"","pos":"v.n.","def":"v.n. To burn brightly, &c. ( = dhakdhakānā, q.v.).","pg":566,"qv":["dhakdhakānā"],"fq":0},{"u":"دگدگاٿ","d":"दगदगाट","r":"dagdagāṭ","src":"Hindi","ety":"","pos":"s.f.","def":"s.f. = dagdagāhaṭ, q.v.","pg":522,"qv":["dagdagāhaṭ"],"fq":0},{"u":"دگدهہ","d":"दग्ध","r":"dagdha","src":"Sanskrit","ety":"","pos":"adj.","def":"adj. (f. -ā), Burnt, consumed by fire, scorched, singed; cauterized; hurt, wounded, sore, grieved; unlucky, unpropitious; cunning","pg":522,"subs":[["dagdhākshar","(˚dha+ak˚), see dhadhać-ćhar",0],["dagdha-kāk","s.m. A black crow, a raven.",0]],"fq":0},{"u":"دگدها","d":"दग्धा","r":"dagdhā","src":"Hindi","ety":"S. दग्ध+कः","pos":"adj.","def":"adj. = dagdha, q.v.","pg":522,"qv":["dagdha"],"chain":[["Sanskrit","दग्ध"]],"fq":0},{"u":"ڐگا","d":"डग्गा","r":"ḍaggā","src":"Hindi","ety":"ḍag, q.v.+S. aff. अ+कः","pos":"","def":"s.m. lit. 'Taking long strides,' or 'having long legs'; longshanks; a horse, &c. that takes long steps or strides, a lean long-legged horse, a Rosinante (also written ḍhaggā; cf. ḍheṅkā).","pg":565,"chain":[["Sanskrit","aff"]],"fq":0},{"u":"داغي","d":"","r":"dāg̠ī","src":"Persian","ety":"dāg̠+ī = Zend aêna = S. इन्","pos":"adj.","def":"adj. Marked, spotted, stained; branded, sullied, disgraced, dishonoured; spoiled, damaged","pg":501,"subs":[["dāg̠ī karnā","v.t. To spot, to stain; to blemish; to brand, stigmatize, disgrace, dishonour.",1]],"chain":[["Sanskrit","इन्"]],"fq":0},{"u":"دغيلا","d":"दग़ीला","r":"dag̠īlā","src":"Hindi","ety":"dāg̠, q.v.+Prk. इल्लओ = S. इल+कः","pos":"adj.","def":"adj. (f. -ī), Marked, spotted, stained ( = dāg̠-dār).","pg":519,"chain":[["Prakrit","इल्लओ"],["Sanskrit","इल"]],"fq":0},{"u":"دغيلا","d":"","r":"dagīlā, dag̠īla, dag̠īlat","src":"Hindi","ety":"for A. دغيلة dag̠īlat","pos":"adj.","def":"adj. Deceitful, &c. ( = dag̠al).","pg":519,"chain":[["Arabic","دغيلة"]],"fq":0},{"u":"دغيله","d":"","r":"dag̠īla, dagīlā, dag̠īlat","src":"Persian","ety":"for A. دغيلة dag̠īlat","pos":"adj.","def":"adj. Deceitful, &c. ( = dag̠al).","pg":519,"chain":[["Arabic","دغيلة"]],"fq":0},{"u":"دغلا","d":"","r":"dag̠lā","src":"Hindi","ety":"","pos":"s.m.","def":"s.m. = دگلا daglā, q.v.","pg":519,"qv":["daglā"],"fq":0},{"u":"دگلا","d":"दगला","r":"daglā","src":"Hindi","ety":"","pos":"s.m.","def":"s.m. A coat or vest (angarkhā) padded with cotton, a quilted coat or vest.","pg":522,"fq":0},{"u":"ڐگمگ","d":"डगमग","r":"ḍagmag, ḍigmag, ḍigmig, ḍagmagā, ḍigmagā, ḍag-ḍag","src":"Hindi","ety":"see ḍag-ḍag","pos":"adj.","def":"adj. Shaking, shaky, tottering, trembling, tremulous, rolling, reeling, swaying from side to side; unsteady, wavering, vacillating.","pg":566,"fq":0},{"u":"ڐگمگا","d":"डगमगा","r":"ḍagmagā, ḍigmagā, ḍag-ḍag, ḍagmag, ḍigmag, ḍigmig","src":"Hindi","ety":"see ḍag-ḍag","pos":"adj.","def":"adj. Shaking, shaky, tottering, trembling, tremulous, rolling, reeling, swaying from side to side; unsteady, wavering, vacillating.","pg":566,"fq":0},{"u":"ڐگمگاهٿ","d":"डगमगाहट","r":"ḍagmagāhaṭ, ḍigmagāhaṭ, ḍigmigāhaṭ","src":"Hindi","ety":"ḍagmagā(nā)+āhaṭ = āwaṭ = Prk. एअव्वअट्टं = S. (इ)तव्य+क+त्वं","pos":"s.f.","def":"s.f. Shaking, tottering, trembling, swaying, rolling; shivering, quaking.","pg":566,"chain":[["Prakrit","एअव्वअट्टं"]],"fq":0},{"u":"دگمگانا","d":"दगमगाना","r":"dagmagānā","src":"Hindi","ety":"","pos":"v.n.","def":"v.n. = ḍagmagānā, q.v.","pg":522,"qv":["ḍagmagānā"],"fq":1},{"u":"ڐگمگانا","d":"डगमगाना","r":"ḍagmagānā, ḍigmagānā, ḍigmigānā, ḍagmag","src":"Hindi","ety":"see ḍagmag","pos":"v.n.","def":"v.n. To shake, totter, tremble, stagger, reel; to shiver, quake, quail (with fear); to sway or roll (in walking), to move with a twisting wanton gait, to walk or move affectedly.","pg":566,"fq":1},{"u":"داغنا","d":"","r":"dāg̠nā","src":"Hindi","ety":"dāg̠, q.v.+nā = Prk. अणअं = S. अनीयं","pos":"v.t.","def":"v.t. To mark by burning with a hot iron, to brand, to cauterize; — to fire (a gun, &c.)","pg":501,"subs":[["dāg̠-denā","v.t. (intens.), To brand, &c. ( = dāg̠nā)",1],["dāg̠ karnā","v.t. To heat, warm, brown (ghī, &c.).",1]],"chain":[["Prakrit","अणअं"],["Sanskrit","अनीयं"]],"fq":1},{"u":"داگنا","d":"दागना","r":"dāgnā, dāg, dāg̠, dāg̠nā","src":"Hindi","ety":"","pos":"","def":"v.t. = H داگ दाग dāg, s.m. corr. of dāg̠; and dāg̠nā, qq.v.","pg":501,"reg":["corrupted form"],"fq":1},{"u":"دغنا","d":"दग़ना","r":"dag̠nā, dāg̠nā","src":"Hindi","ety":"fr. the trans. dāg̠nā","pos":"v.n.","def":"v.n. To be branded with a hot iron, to be marked; — to be fired off (as a gun).","pg":519,"fq":1},{"u":"دغوليا","d":"","r":"dag̠oliyā","src":"Hindi","ety":"prob. dag̠ā+Prk. उल्लइओ = S. उल+इकः (इन्+कः)","pos":"s.m.","def":"s.m. An impostor.","pg":519,"chain":[["Prakrit","उल्लइओ"],["Sanskrit","उल"]],"fq":0},{"u":"دگڙا","d":"दगड़ा","r":"dagṛā","src":"Hindi","ety":"","pos":"s.m.","def":"s.m. Road, way, highway ( = ḍagar).","pg":522,"fq":0},{"u":"ڐگرا","d":"डगरा","r":"ḍagrā, ḍagar, ḍag, ḍagar batānā, ko, aur ḍagar ćalnā","src":"Hindi","ety":"","pos":"","def":"s.m. = H ڐگر डगर ḍagar, s.f. (fr. ḍag, q.v.), Highway, way, road, path, track; a wide path between fields (for the passage of cattle, &c.)","pg":566,"subs":[["ḍagar batānā","(-ko), To show or point out the road, to direct, to guide",1],["aur ḍagar ćalnā","'To take another road or path'; to mislead, deceive, trick, cheat.",0]],"qv":["ḍag"],"fq":0},{"u":"ڐگرا","d":"डगरा","r":"ḍagrā, ḍagrānā","src":"Hindi","ety":"fr. ḍagrānā","pos":"s.m.","def":"s.m. A round-bottomed basket or tray (made of split bamboo; used to hold rice, flour, &c., and also to winnow with).","pg":566,"fq":0},{"u":"دگڙانا","d":"दगड़ाना","r":"dagṛānā","src":"Hindi","ety":"caus. of next","pos":"v.t.","def":"v.t. To rock; to roll; to propel ( = ḍagrānā).","pg":522,"fq":0},{"u":"ڐگرانا","d":"डगराना","r":"ḍagrānā, ḍagarnā","src":"Hindi","ety":"caus. of ḍagarnā","pos":"v.t.","def":"v.t. To put in motion, to propel, to roll.","pg":566,"fq":0},{"u":"ڐگري","d":"डगरी","r":"ḍagrī, dagrā","src":"Hindi","ety":"","pos":"","def":"s.f. dim. of dagrā, q.v.","pg":566,"qv":["dagrā"],"fq":0},{"u":"داه","d":"दाह","r":"dāh","src":"Hindi","ety":"Prk. दाहो; S. दाहः, rt. दह्","pos":"s.f.","def":"s.f. Burning; combustion, conflagration; cauterizing; cautery; — fire; the sensation of burning, internal heat, feverish or morbid heat; inflammation; — ardour; heart-burning, envy, jealousy","pg":504,"subs":[["dāh-jvar","s.m. Inflammatory fever",0],["dāh denā","(-ko), To apply fire (to), to light (the funeral pile)",1],["dāh-rakhnā","v.n. To bear envy, &c., to be envious or jealous; to grudge",1],["dāh-sar","s.m. A place where dead bodies are burnt",0],["dāh-karm","dāh-karan, s.m. = dāh-kriyā, q.v.",0],["dāh karnā","v.t. To burn, &c.",1],["dāh-kriyā","s.f. The act, or the ceremony, of burning a corpse",0],["dāh-haraṇ","s.m. 'Removing heat'; the root of the fragrant grass Andropogon muricatus (which is woven into screens and kept wet for the purpose of tempering the hot winds; see ḵẖas-ḵẖas).",0]],"chain":[["Prakrit","दाहो"],["Sanskrit","दाहः"]],"fq":2},{"u":"ده","d":"दह","r":"dah","src":"Hindi","ety":"Prk. दहो; S. द्रहः, prob. a Prākrit form of S. ह्रदः","pos":"s.m.","def":"s.m. Very deep water, a deep pool; depth, abyss; pool or eddy (in a river), whirlpool, vortex; a lake; a river (e.g. kaṅwal-dah, 'A pool or lake of lotuses or water-lilies'; kālī-dah, 'the river Kālī').","pg":537,"chain":[["Prakrit","दहो"],["Sanskrit","द्रहः"],["Sanskrit","ह्रदः"]],"fq":2},{"u":"ده","d":"","r":"dah","src":"Persian","ety":"Pehl. dah; Zend daśan, nom. daśa; S. दशन्, दश","pos":"adj.","def":"adj. Ten (also used, for daś or das, by some of the old Hindī poets, as Ćand, &c., and in Hindī compounds)","pg":537,"subs":[["dah-bāshī","(bāshī, fr. T. bāsh, 'head'), s.m. A commander of ten men; a person having a place of trust; a valet",0],["dah-ćand","adj. Ten-fold, ten times",0],["dah-ćandagī","s.f. A ten-fold (return, — used in returning a salutation)",0],["dah dar dunyā ṣad dar āḵẖirat","prov. 'Ten in this world, a hundred in the next'; charity will be returned ten-fold in the next world (used as a benediction by mendicants; — sattar, 'seventy,' is sometimes substituted for ṣad, 'hundred')",0],["dah dar dah","'Ten by ten,' ten cubic yards (of water, — such being regarded as pure according to the ḥadīs̤ or Mohammadan law)",0],["dah-dila","adj. 'Having ten hearts'; fickle, inconstant, faithless; — brave, courageous, bold",0],["dah-roza","s.m. An aggregate of ten days, a decade",0],["dah-sāla","adj. Of ten years; decennial",0],["dah-sanī","adj. Of or for ten years; — s.f. A book comprising the collections, accounts, registers, &c. of ten years",0],["dah-serā","s.m. A weight of ten ser or seers",0],["dah-marda","adj. & s.m. Consisting of, or capable of carrying, ten men; — a company or body of ten men; a cart (smaller than a gāṛī or ćhakṛā), capable of carrying ten men",0],["dah-mannī","adj. Holding ten man or maunds",0],["dah-nīmī","s.f. lit. 'Half of ten'; five per cent.",0],["dah-yak","s.m., or dah-yakī, s.f. A tenth part, a tithe, one in ten; an allowance of ten per cent.",0]],"chain":[["Pahlavi","dah"],["Sanskrit","दशन्"]],"fq":2},{"u":"ڐاه","d":"डाह","r":"ḍāh","src":"Hindi","ety":"Prk. डाहो or दाहो; S. दाहः, rt. दह्; — or fr. ḍāhnā, q.v.","pos":"s.f.","def":"s.f. Burning, rage, heart-burning, jealousy, envy, malice, spite, rancour","pg":563,"subs":[["ḍāh khānā","To be jealous, or envious, &c.",1]],"chain":[["Prakrit","डाहो"],["Sanskrit","दाहः"]],"fq":2},{"u":"دها","d":"","r":"dahā, dah","src":"Persian","ety":"fr. dah","pos":"s.m.","def":"s.m. The first ten days of the Moharram (syn. ʻashara; ʻāshūrā); — the models of the tombs of Hasan and Husain, or the model of a building containing the tombs, which are carried about in procession during those ten days. (On the tenth day the tombs are buried, or in some places, thrown into water: the building, if made of cheap materials, shares the same fate; if costly, it is carried back and deposited in the dargāh or Karbalā.)","pg":537,"syn":["ʻashara"],"fq":1},{"u":"داها","d":"","r":"dāhā, dahā","src":"Hindi","ety":"","pos":"","def":"s.m. corr. of dahā, q.v.","pg":504,"qv":["dahā"],"reg":["corrupted form"],"fq":1},{"u":"دهائي","d":"दहाई","r":"dahāʼī","src":"Hindi","ety":"fr. S. दशक+इका","pos":"s.f.","def":"s.f. The figure ten; tenth part; the tens, the tens' place (in numeration), the decimal place (of figures), a decimal.","pg":540,"chain":[["Sanskrit","दशक"]],"fq":0},{"u":"دهج","d":"दहज","r":"dahaj, dihez","src":"Hindi","ety":"","pos":"","def":"s.m. corr. of dihez, q.v.","pg":540,"qv":["dihez"],"reg":["corrupted form"],"fq":0},{"u":"داهك","d":"दाहक","r":"dāhak","src":"Sanskrit","ety":"","pos":"adj.&s.m.","def":"adj. & s.m. (f. -ikā), Burning, kindling, setting on fire; causing heat or combustion; incendiary; inflammatory; cauterizing, caustic; — an incendiary; — the plant Plumbago zeylanica.","pg":504,"fq":0},{"u":"دهك","d":"दहक","r":"dahak","src":"Hindi","ety":"S. दह्+कृ","pos":"s.f.","def":"s.f. Burning, blazing, conflagration; glow; ardour, fervency, fervour.","pg":545,"chain":[["Sanskrit","दह्"]],"fq":0},{"u":"ڐهك","d":"डहक","r":"ḍahak","src":"Hindi","ety":"S. दरक; or द्रहक","pos":"s.m.","def":"s.m. Cave, cavern; abyss; pitfall.","pg":571,"chain":[["Sanskrit","दरक"]],"fq":0},{"u":"دهاك","d":"","r":"dahāk, dah, dahākā","src":"Persian","ety":"fr. dah; cf. dahākā","pos":"s.m.","def":"s.m. The place of tens (in Numeration).","pg":538,"fq":0},{"u":"دهاکا","d":"दहाका","r":"dahākā","src":"Hindi","ety":"S. दशक+कं","pos":"s.m.","def":"s.m. A collection or aggregate of ten; — the tens' place, the tens (in Numeration).","pg":538,"chain":[["Sanskrit","दशक"]],"fq":0},{"u":"دهاکا","d":"दहाका","r":"dahākā, dahnā","src":"Hindi","ety":"prob. from dahnā, 'To burn,' q.v.","pos":"s.m.","def":"s.m. Loss, damage; blow, shock; grief, sorrow, affliction.","pg":538,"fq":0},{"u":"دهکنا","d":"दहकना","r":"dahaknā","src":"Hindi","ety":"dahak˚ = Prk. दहक्क(इ), or दहक्के(इ), fr. S. दह+कृ","pos":"v.n.","def":"v.n. To burn, to blaze; to be burnt; to be ruined or destroyed, to be lost; to regret, grieve, be consumed with regret, &c.","pg":545,"chain":[["Prakrit","दहक्क"],["Sanskrit","दह"]],"fq":0},{"u":"ڐهکنا","d":"डहकना","r":"ḍahaknā","src":"Hindi","ety":"","pos":"v.t.","def":"v.t. = ḍahkānā, q.v.","pg":571,"qv":["ḍahkānā"],"fq":0},{"u":"دهل","d":"दहल","r":"dahal, dahalnā","src":"Hindi","ety":"v.n. fr. dahalnā, q.v.","pos":"s.f.","def":"s.f. Shaking tremulously, shaking, trembling, quaking, tremor; fear, apprehension, dread; — shifting sand, quicksand, &c. ( = daldal). (The name of Dahlī or Dehlī is said to be derived from this word; the ground on which the city was built being so loose and infirm that tent-pins could not be fixed in it.)","pg":545,"fq":0},{"u":"دهلنا","d":"दहलना","r":"dahalnā","src":"Hindi","ety":"dahal˚, prob. = Prk. दहड = S. दह+ल or र","pos":"v.n.","def":"v.n. To shake, tremble, quake; to fear, be alarmed or terrified","pg":546,"subs":[["dahal-jānā","v.n. Idem.",1]],"chain":[["Prakrit","दहड"],["Sanskrit","दह"]],"fq":0},{"u":"دهام","d":"दहाम","r":"dahām","src":"Hindi","ety":"S. दश+ग्रामं?","pos":"s.m.","def":"s.m. A collection or aggregate of ton (e.g. tīn dahām tīs).","pg":539,"chain":[["Sanskrit","दश"]],"fq":0},{"u":"دهم","d":"दहम","r":"daham","src":"Hindi","ety":"fr. S. दह्","pos":"adj.","def":"adj. Burnt to ashes, burnt out, extinguished.","pg":546,"chain":[["Sanskrit","दह्"]],"fq":0},{"u":"داهن","d":"दाहन","r":"dāhan","src":"Sanskrit","ety":"","pos":"s.m.","def":"s.m. Causing to burn, setting fire to, burning, inflaming; cauterizing.","pg":504,"fq":1},{"u":"دهان","d":"","r":"dahān","src":"Persian","ety":"","pos":"s.m.","def":"s.m. The mouth; an orifice.","pg":539,"fq":1},{"u":"دهن","d":"दहन","r":"dahan","src":"Sanskrit","ety":"","pos":"s.m.","def":"s.m. (but f. in Hindī), Fire; burning, combustion, conflagration; sultriness; — s.m. Agni, the god of fire; lead-wort, Plumbago zeylanica; the marking nut, Anacardium officinarum; — a gold coin (in value six rupees)","pg":547,"subs":[["dahanopal","(˚na+up˚), s.m. 'Fire-stone'; the sun-gem; a crystal lens",0],["dahan karnā","v.t. To burn.",1]],"fq":1},{"u":"دهن","d":"","r":"dahan, dahān","src":"Persian","ety":"","pos":"","def":"s.m. contrac. of dahān, q.v.","pg":547,"qv":["dahān"],"fq":1},{"u":"دهانه","d":"","r":"dahāna, dahān","src":"Persian","ety":"rel. n. fr. dahān","pos":"s.m.","def":"s.m. Mouth (of a water-bag, or drain, or watercourse, or river, &c.), opening (of a valley, &c.); — bit (of a bridle); anything which covers the mouth.","pg":539,"fq":0},{"u":"دهانا","d":"दहाना","r":"dahānā, dahnā","src":"Hindi","ety":"caus. of dahnā","pos":"v.t.","def":"v.t. To set fire to, to burn","pg":539,"subs":[["dahā-denā","v.t. intens. of and = dahānā.",1]],"fq":0},{"u":"دهنوپل","d":"दहनोपल","r":"dahanopal","src":"Sanskrit","ety":"","pos":"s.m.","def":"s.m. See s.v. dahan.","pg":549,"fq":0},{"u":"ڐهر","d":"डहर","r":"ḍahar, ḍagar, ḍahrā","src":"Hindi","ety":"","pos":"","def":"s.m-1˚ = ḍagar, q.v.; — 2˚ = ḍahrā, q.v.","pg":571,"qv":["ḍagar","ḍahrā"],"fq":0},{"u":"دهاڙ","d":"दहाड़","r":"dahāṛ, dahāṛnā","src":"Hindi","ety":"v.n. of dahāṛnā, q.v.","pos":"s.f.","def":"s.f. Roaring, thundering; roar, loud noise or cry","pg":538,"subs":[["dahāṛeṅ mārnā","dahāṛeṅ mār-kar ronā, To cry aloud, to weep bitterly ( = dāṛh mār-kar ronā).",1]],"fq":0},{"u":"دهر","d":"दहर","r":"dahar, dahrī, ḍahrī","src":"Hindi","ety":"","pos":"","def":"s.m.? = dahrī, and ḍahrī, q.v.","pg":541,"qv":["ḍahrī"],"fq":0},{"u":"دهار","d":"दहार","r":"dahār, dihār","src":"Hindi","ety":"","pos":"s.m.","def":"s.m. = dehir, q.v.","pg":538,"qv":["dehir"],"fq":0},{"u":"دهش","d":"","r":"dahash","src":"Arabic","ety":"inf. n. of دهش","pos":"s.m.f.","def":"s.m.f. Astonishment, amazement, consternation; — adj. Astonished, amazed, stupefied, confounded, bewildered, struck with consternation.","pg":544,"fq":0},{"u":"دهت","d":"दहत्","r":"dahat","src":"Sanskrit","ety":"","pos":"adj.","def":"adj. Burning, scorching.","pg":540,"fq":0},{"u":"ڐهڐها","d":"डहडहा","r":"ḍahḍahā","src":"Hindi","ety":"fr. next, q.v.","pos":"adj.","def":"adj. (f. -ī), Glowing, bright, blooming, flourishing, fresh, verdant, green, pleasant, pleasing; overpowering, excessive, great.","pg":571,"fq":0},{"u":"ڐهڐهانا","d":"डहडहाना","r":"ḍahḍahānā","src":"Hindi","ety":"","pos":"v.n.","def":"v.n. To glow, shine; to bloom, blossom, flourish.","pg":571,"fq":0},{"u":"دهدل","d":"दहदल","r":"dahdal","src":"Hindi","ety":"","pos":"s.f.","def":"s.f. (m.?) = daldal, q.v.","pg":541,"qv":["daldal"],"fq":0},{"u":"دهے","d":"","r":"dahe, dahā","src":"Hindi","ety":"","pos":"","def":"s.m. pl. = dahā, q.v.","pg":553,"qv":["dahā"],"fq":0},{"u":"دهيج","d":"दहेज","r":"dahej, dihez","src":"Hindi","ety":"","pos":"","def":"s.m. corr. of dihez, q.v.","pg":553,"qv":["dihez"],"reg":["corrupted form"],"fq":0},{"u":"دهيل","d":"दहेल","r":"dahel, dahiyal","src":"Hindi","ety":"","pos":"s.m.","def":"s.m. = daheṛ, q.v.","pg":554,"qv":["daheṛ"],"fq":0},{"u":"دهيلا","d":"दहेला","r":"dahelā","src":"Hindi","ety":"S. दश+इल+कः","pos":"s.m.","def":"s.m. (dialec.), The ten (at cards).","pg":554,"reg":["dialectal"],"chain":[["Sanskrit","दश"]],"fq":0},{"u":"دهيلي","d":"दहेली","r":"dahelī","src":"Hindi","ety":"","pos":"s.f.","def":"s.f. = dihlī or děhlī, q.v.","pg":554,"qv":["děhlī"],"fq":0},{"u":"دهينڐي","d":"दहेण्डी","r":"daheṅḍī, dahaiṅḍī, daheṅṛī","src":"Hindi","ety":"S. दधि+भाण्ड+इका","pos":"s.f.","def":"s.f. A vessel in which milk is coagulated, or in which coagulated milk is kept.","pg":554,"chain":[["Sanskrit","दधि"]],"fq":0},{"u":"دهينگر","d":"दहेंगर","r":"daheṅgar, dahī, dahaiṅḍī","src":"Hindi","ety":"fr. dahī; cf. dahaiṅḍī","pos":"s.m.","def":"s.m. A vessel for carrying coagulated or sour milk (especially at festivals).","pg":554,"fq":0},{"u":"دهينڙي","d":"दहेंड़ी","r":"daheṅṛī","src":"Hindi","ety":"S. दधि+भाण्ड+इका","pos":"s.f.","def":"s.f. A vessel in which milk is coagulated, or in which coagulated milk is kept.","pg":554,"chain":[["Sanskrit","दधि"]],"fq":0},{"u":"دهيڙ","d":"दहेड़","r":"daheṛ","src":"","ety":"prob. fr. S. दग्ध; but cf. ḍheṛ","pos":"s.m.","def":"s.m. A raven; a crow; a species of bird, Coracias; — the dial bird of Southern India, Copsychus saularis (a beautiful songster common throughout India).","pg":554,"chain":[["Sanskrit","दग्ध"]],"fq":0},{"u":"دهيڙي","d":"दहेड़ी","r":"daheṛī","src":"Hindi","ety":"","pos":"s.f.","def":"s.f. = daheṅḍī, q.v.","pg":554,"qv":["daheṅḍī"],"fq":0},{"u":"دهيزو","d":"","r":"dahezū","src":"Hindi","ety":"dahez, q.v.+S. उकः","pos":"adj.","def":"adj. Of or belonging to a dowry; — flimsy, gim-crack.","pg":554,"chain":[["Sanskrit","उकः"]],"fq":0},{"u":"داهي","d":"दाही","r":"dāhī","src":"Sanskrit","ety":"","pos":"adj.","def":"adj. (f. -inī), Burning, setting on fire; burning hot; tormenting, paining.","pg":504,"fq":1},{"u":"داهی","d":"","r":"dāhī","src":"Arabic","ety":"act. part. n. of دهی 'to possess intelligence'","pos":"adj.","def":"adj. Possessing intelligence or sagacity, cunning, knowing, skilful, shrewd, penetrating.","pg":504,"fq":1},{"u":"ڐاهي","d":"डाही","r":"ḍāhī","src":"Hindi","ety":"Prk. डाहिओ; S. दाही+कः","pos":"adj.&s.m.","def":"adj. & s.m. (f. -inī), Jealous, envious, malicious, spiteful, rancorous; — a malicious person, &c.","pg":563,"chain":[["Prakrit","डाहिओ"],["Sanskrit","दाही"]],"fq":1},{"u":"دهي","d":"दही","r":"dahī, dhaʼī","src":"Hindi","ety":"Prk. दहिअं; S. दधि+कं","pos":"s.m.","def":"s.m. Thick sour milk, coagulated milk (called 'tire or tyre' in India)","pg":553,"subs":[["dahī jamānā","To make coagulated milk",1],["dahī jamnā","v.n. To be or become coagulated (milk)",0],["dahī-wālā; s.m.","(f. -ī), A seller of dahī or coagulated milk.",0]],"chain":[["Prakrit","दहिअं"],["Sanskrit","दधि"]],"fq":1},{"u":"داهنا","d":"दाहिना","r":"dāhinā, dāhnā","src":"Hindi","ety":"Prk. दाहिणओ; S. दक्षिण+कः","pos":"adj.","def":"adj. Right (hand, &c.) = dahinā, q.v.","pg":504,"qv":["dahinā"],"chain":[["Prakrit","दाहिणओ"],["Sanskrit","दक्षिण"]],"fq":1},{"u":"دهنا","d":"दहिना","r":"dahinā, dahnā","src":"Hindi","ety":"Prk. दाहिणओ; S. दक्षिण+कः","pos":"adj.","def":"adj. (f.-ī), Right (hand, or side, &c.)","pg":547,"subs":[["dahināvart = dakshiṇāvart","q.v.s.v. dakshiṇa",0],["dahnc obl. of dahnā; Prk. dāhiṇe; S. dakshiṇe)","adv. To the right; on the right; at the right.",0]],"chain":[["Prakrit","दाहिणओ"],["Sanskrit","दक्षिण"]],"fq":1},{"u":"دهت","d":"दहित","r":"dahit","src":"Sanskrit","ety":"","pos":"part.","def":"part. Burnt, scorched.","pg":540,"fq":0},{"u":"ڐهکانا","d":"डहकाना","r":"ḍahkānā","src":"Hindi","ety":"","pos":"v.t.","def":"v.t. To lead astray, to mislead; to deceive, disappoint, baulk, tantalize, &c. ( = bahkānā, q.v.).","pg":571,"qv":["bahkānā"],"fq":0},{"u":"ڐهکانا","d":"डहकाना","r":"ḍahkānā","src":"Hindi","ety":"","pos":"v.t.","def":"v.t. To throw away uselessly, to spoil (cf. ḍahnā; ḍhānā).","pg":571,"fq":0},{"u":"دهکانا","d":"दहकाना","r":"dahkānā, dahaknā","src":"Hindi","ety":"caus. of dahaknā","pos":"v.t.","def":"v.t. To burn, kindle; to heat (iron, &c.), to inflame; to cause to regret or grieve; to ruin, destroy, lose.","pg":545,"fq":0},{"u":"دهلا","d":"दहला","r":"dahlā","src":"Hindi","ety":"dah = das+lā = alā = Prk. अडओ = S. ल+कः","pos":"s.m.","def":"s.m. Ten (at cards), the ten (of a suit of cards).","pg":545,"chain":[["Prakrit","अडओ"],["Sanskrit","ल"]],"fq":0},{"u":"دهلان","d":"दहलान","r":"dahlān","src":"Hindi","ety":"","pos":"s.m.","def":"s.m. Name of a tribe of Jagas in the Upper Doāb.","pg":545,"fq":0},{"u":"دهلان","d":"","r":"dahlān, dalān","src":"Hindi","ety":"","pos":"","def":"s.m. corr. of dalān, q.v.","pg":545,"qv":["dalān"],"reg":["corrupted form"],"fq":0},{"u":"دهلانا","d":"दहलाना","r":"dahlānā, dahalnā","src":"Hindi","ety":"caus. of dahalnā","pos":"v.t.","def":"v.t. To shake, to agitate; to cause to tremble or quake.","pg":545,"fq":0},{"u":"دهليز","d":"","r":"dahlīz, děhlīz, dihlīz","src":"Persian","ety":" = S. देहली; — A. dihlīz, fr. the Pers.","pos":"s.f.","def":"s.f. Threshold; portico, entrance hall, vestibule","pg":546,"subs":[["dahlīz jhāṅknā","v.n. = dahlīz laṅgnā",0],["dahlīz-kā kuttā","s.m. The dog of the porch, house-dog; — a hanger-on, parasite",0],["dahlīz khundlānā","s.m. lit. 'Treading the threshold'; a ceremonial visit paid by a young man about to be married to the parents of his intended bride",1],["dahlīz laṅgnā","(-kī), To cross the threshold (of), to pay a visit (to).",0]],"chain":[["Sanskrit","देहली"],["Arabic","dihlīz"]],"fq":1},{"u":"داهنا","d":"दाहना","r":"dāhnā","src":"Hindi","ety":"dāh˚ = Prk. दाह(इ) or दाहे(इ) = S. दाहय(ति), caus. fr. rt. दह्;+nā = Prk. अणअं = S. अनीयं","pos":"v.t.","def":"v.t. To set fire to, to burn, to kindle.","pg":504,"chain":[["Prakrit","दाह"],["Sanskrit","दाहय"],["Prakrit","अणअं"],["Sanskrit","अनीयं"]],"fq":1},{"u":"دهنا","d":"दहना","r":"dahnā","src":"Hindi","ety":"Prk. दहणआं = S. दहनीयं, rt. दह्","pos":"v.n.","def":"v.n. To be burnt; to be inflamed; to burn, blaze.","pg":547,"chain":[["Prakrit","दहणआं"],["Sanskrit","दहनीयं"]],"fq":1},{"u":"دهنا","d":"दहना","r":"dahnā","src":"Hindi","ety":"","pos":"v.n.","def":"v.n. = ḍhanā or ḍhahnā, q.v.","pg":547,"qv":["ḍhahnā"],"fq":1},{"u":"ڐاهنا","d":"डाहना","r":"ḍāhnā","src":"Hindi","ety":"ḍāh˚ = Prk. डाह(इ) or डाहे(इ), fr. डाह = S. दाह","pos":"v.n.","def":"v.n. To be hot, to burn; to burn with rage or envy, &c., to be malicious, or spiteful; to be heated or fused (as metals).","pg":563,"chain":[["Prakrit","डाह"],["Sanskrit","दाह"]],"fq":1},{"u":"دهنون","d":"दहनौं","r":"dahnauṅ","src":"Hindi","ety":"","pos":"v.n.","def":"v.n. (Braj.) = dahnā, q.v.","pg":549,"qv":["dahnā"],"fq":0},{"u":"دهنيه","d":"दहनीय","r":"dahnīya","src":"Sanskrit","ety":"","pos":"adj.&s.m.","def":"adj. & s.m. To be burnt, fit to be burnt; combustible; — anything to be burnt.","pg":549,"fq":0},{"u":"دهوکا","d":"दहोका","r":"dahokā, dhokā","src":"Hindi","ety":"","pos":"s.m.","def":"s.m. A measure of about ten handfuls (of grain, &c.).","pg":551,"fq":0},{"u":"دهوترا","d":"दहोतरा","r":"dahotarā, dahotrā","src":"Hindi","ety":"S. दश+उत्तर+कं","pos":"s.m.","def":"s.m. Tenth part, tithe, ten per cent., an allowance or tax of ten per cent.","pg":550,"chain":[["Sanskrit","दश"]],"fq":0},{"u":"دهر","d":"","r":"dahr, dahar","src":"Arabic","ety":"","pos":"s.m.","def":"s.m. Time; a long period of time; an age; eternity; fortune, fate; chance, adverse fortune, misfortune, calamity, adversity; danger; — custom, habit, mode, manner; care, solicitude; the world; atheism.","pg":541,"fq":0},{"u":"ڐهرا","d":"डहरा","r":"ḍahrā, ḍahurā","src":"Hindi","ety":"prob. S. दक (for डदक)+धर+कः","pos":"s.m.","def":"s.m. A hole dug for water; hollow or low ground (in which water collects), tank, &c. ( = ḍabrā, ḍābar, q.v.); a water-tank (in a ship), a barrel or cask in which drinking water is kept (in a boat or ship); the part of a boat or ship in which bilge-water collects.","pg":571,"qv":["ḍābar"],"chain":[["Sanskrit","दक"]],"fq":0},{"u":"دهري","d":"","r":"dahrī, dahr","src":"Arabic","ety":"rel. n. fr. dahr","pos":"adj.","def":"adj. Relating to time, or to fortune; secular, temporal; relating to the world, worldly; impious, atheistical.","pg":543,"fq":0},{"u":"دهري","d":"दहरी","r":"dahrī, dahr, ḍahrā, ḍahrī","src":"Hindi","ety":"see dahr; and ḍahrā, ḍahrī","pos":"s.f.","def":"s.f. Stiff clay soil (in low ground), marshy soil.","pg":543,"fq":0},{"u":"ڐهري","d":"डहरी","r":"ḍahrī, ḍahrā","src":"Hindi","ety":"see ḍahrā","pos":"adj.","def":"adj. Marshy; — s.f. Marshy soil, &c. ( = ḍabrā).","pg":571,"fq":0},{"u":"دهريا","d":"","r":"dahrīyā","src":"Hindi","ety":"","pos":"s.m.","def":"s.m. = دهريه dahrīya, q.v.","pg":543,"qv":["dahrīya"],"fq":0},{"u":"دهريه","d":"","r":"dahrīya, dahrī","src":"Persian","ety":"for A. دهرية, fr. dahrī, q.v.","pos":"s.m.","def":"s.m. One who maintains the eternity of matter, a materialist, an atheist.","pg":543,"chain":[["Arabic","دهرية"]],"fq":0},{"u":"دهسني","d":"","r":"dah-sanī","src":"Hindi","ety":"","pos":"adj.&s.f.","def":"adj. & s.f. See s.v. dah, 'ten.'","pg":544,"fq":0},{"u":"دهشت","d":"","r":"dahshat, dahash","src":"Persian","ety":"for A. دهشة, fr. dahash, q.v.","pos":"s.f.","def":"s.f. Consternation, fear, fright, terror, dismay, dread, awe, alarm","pg":545,"subs":[["dahshat-angez","adj. Horrible, terrible, hideous, terrifying, alarming; threatening, intimidating",0],["dahshat denā","(-ko), To frighten, terrify, alarm, &c., to instil dread (into)",1],["dahshat-zada","adj. Terror-stricken, panic-struck, terrified, frightened, alarmed, scared",0],["dahshat khānā","(-se), To be frightened, be afraid, be intimidated, &c.",1],["dahshat-nāk","adj. Alarming, terrifying, &c. ( = dahshat-angez); frightened, &c. ( = dahshat-zada).",0]],"chain":[["Arabic","دهشة"]],"fq":0},{"u":"داهو","d":"दाहु","r":"dāhu, dāh, dāhī, dāʼū","src":"Hindi","ety":"","pos":"","def":"(dialec.); 1˚ = dāh; — 2˚ = dāhī; — 3˚ = dāʼū; qq.v.","pg":504,"reg":["dialectal"],"fq":0},{"u":"ڐاهك","d":"डाहुक","r":"ḍāhuk","src":"Sanskrit","ety":"","pos":"s.m.","def":"s.m. A gallinule.","pg":563,"fq":0},{"u":"دهم","d":"दहम","r":"dahum","src":"Persian","ety":"Pehl. dahum; Zend daśema; S. दशम","pos":"adj.","def":"adj. Tenth.","pg":546,"chain":[["Pahlavi","dahum"],["Sanskrit","दशम"]],"fq":0},{"u":"داعي","d":"","r":"dāʻī","src":"Arabic","ety":"act. part. n. of دعو 'to supplicate,' &c.","pos":"s.m.","def":"s.m. One who prays for the welfare of another, a well-wisher; — a plaintiff, complainant; — one who instigates (another to anything), instigator; author, cause; motive, means.","pg":501,"fq":2},{"u":"دائی","d":"दाई","r":"dāʼī","src":"Hindi","ety":"S. दायिकः i.e. दायिन्+कः","pos":"adj.&s.m.","def":"adj. & s.m. Giving, bestowing; giver, &c. (com. used at the end of comp., e.g. dukh-dāʼī, q.v.).","pg":504,"qv":["dukh-dāʼī"],"chain":[["Sanskrit","दायिकः"]],"fq":2,"ipa":"/d̪ɑː.iː/","wety":"Borrowed from Classical Persian دَایَه (dāya)."},{"u":"دائي","d":"दाई","r":"dāʼī","src":"Hindi","ety":"Prk. दत्तिआ; S. दात्रिका rt. दा","pos":"s.f.","def":"s.f. A nurse; a wet-nurse; a midwife; (local) a maid-servant; — the stand that children run to in playing hide-and-seek","pg":504,"subs":[["dāʼī aṣīl","s.f. A superior maid-servant, a lady's maid",0],["dāʼī-pilāʼī","s.f. A wet-nurse",0],["dāʼī-janāʼī","s.f. A midwife",0],["dāʼī-ko soṅpnā","v.t. To put out to nurse",0],["dāʼī-khilāʼī","s.f. A dry-nurse",0],["dāʼī-garī","s.f. Midwifery.",0]],"chain":[["Prakrit","दत्तिआ"],["Sanskrit","दात्रिका"]],"fq":2},{"u":"دئي","d":"दई","r":"daʼī","src":"Hindi","ety":"S. दाया, rt. dā","pos":"s.f.","def":"s.f. A gift.","pg":554,"chain":[["Sanskrit","दाया"]],"fq":2},{"u":"دئي","d":"दई","r":"daʼī","src":"Hindi","ety":"","pos":"s.m.","def":"s.m. = dāʼī, 'giver,' q.v.","pg":554,"fq":2},{"u":"دئي","d":"दई","r":"daʼī","src":"Hindi","ety":"Prk. दइउ; S. दवं","pos":"s.m.f.","def":"s.m.f. The Deity; a god; destiny, fate; — s.f. Godhead, divinity; — intj. O God! my God! (cf. Fr. mon Dieu!)","pg":554,"subs":[["daʼī-kā dūsrā","s.m. 'A god's peer'; a demon, devil ( = deʼo)",0],["daʼī lagnā","(-ko), To be visited by divine wrath, to be unfortunate",1],["daʼī-mārā","adj. & s.m. (f. -ī), Struck by the Deity, fate-stricken, accursed; — an accursed one.",0]],"chain":[["Prakrit","दइउ"],["Sanskrit","दवं"]],"fq":2},{"u":"دئي","d":"दई","r":"daʼī","src":"Hindi","ety":"","pos":"s.f.","def":"s.f. 1˚ = dayā (e.g. nir-daʼī); — 2˚ = daiyā, qq.v.","pg":554,"fq":2},{"u":"دئي","d":"दई","r":"daʼī","src":"Hindi","ety":"","pos":"part.","def":"part. (dialec.) = dī, q.v.","pg":554,"qv":["dī"],"reg":["dialectal"],"fq":2},{"u":"دي","d":"","r":"dai, daʼe","src":"Persian","ety":"","pos":"s.m.","def":"s.m. The tenth month of the solar year (when the sun is in the sign Capricorn), December; the beginning of winter, winter.","pg":555,"fq":2},{"u":"ديبي","d":"दैबी","r":"daibī","src":"Hindi","ety":"","pos":"adj.&adv.","def":"adj. & adv. = daivī, q.v.","pg":555,"qv":["daivī"],"fq":0},{"u":"دايج","d":"दाइज","r":"dāʼij","src":"Hindi","ety":"S. दाय+आद्यकं","pos":"s.m.","def":"s.m. = next, q.v.","pg":505,"qv":["next"],"chain":[["Sanskrit","दाय"]],"fq":0},{"u":"ديجور","d":"","r":"daijūr, dāj, imāla, war, ūr","src":"Persian","ety":"fr. A. dāj, rt. دجو 'to be dark,' by imāla+P. aff. war or ūr; — A. also daijūr","pos":"adj.&s.m.","def":"adj. & s.m. Dark, pitch dark, black; — the night of conjunction of sun and moon; a dark night without moonlight; — anything black; darkness, obscurity.","pg":556,"root":"د ج و","chain":[["Arabic","dāj"],["Persian","aff"],["Arabic","also"]],"fq":0},{"u":"دائم","d":"","r":"dāʼim","src":"Arabic","ety":"act. part. n. of دام (for دوم","pos":"adj.&adv.","def":"adj. & adv. Continuing, lasting; continuing always, continual, &c. (see dāʼimī, the more com. form.); — continually, always, perpetually ( = dāʼimaṉ)","pg":505,"subs":[["dāʼimuʼl-ḥabs","Imprisonment for life; perpetually imprisoned",0],["dāʼimuʼl-ḵẖamr","adj. & s.m. Perpetually drinking wine; — a sot, a drunkard",0],["dāʼimuʼl-maraẓ","adj. Always sick.",0]],"fq":0,"sh":5531},{"u":"دائمًا","d":"","r":"dāʼimaṉ, dāʼim","src":"Arabic","ety":"acc. of dāʼim","pos":"adv.","def":"adv. Continually, perpetually, for ever.","pg":505,"fq":0},{"u":"دائمی","d":"","r":"dāʼimī, dāʼim","src":"Arabic","ety":"rel. n. fr. dāʼim","pos":"adj.","def":"adj. Continual, lasting, enduring, permanent, durable, standing; prolonged; perpetual, in perpetuity, continuing always or for ever, unintermittent (as fever), ceaseless, eternal, everlasting; — s.f. Permanence; perpetuity, &c. ( = dāʼimīyat, q.v.).","pg":505,"qv":["dāʼimīyat"],"fq":0},{"u":"دائميت","d":"","r":"dāʼimīyat, dāʼimī","src":"Persian","ety":"for A. دائمية, abst. s. fr. dāʼimī","pos":"s.f.","def":"s.f. Continuance, durableness, permanence; perpetuity, eternity.","pg":505,"chain":[["Arabic","دائمية"]],"fq":0},{"u":"دائن","d":"","r":"dāʼin","src":"Arabic","ety":"act. part. of دان (for دين","pos":"s.m.","def":"s.m. One who borrows, or takes upon credit; a debtor; — one who gives credit, a creditor.","pg":505,"fq":0},{"u":"دائين","d":"दाईं","r":"dāʼīṅ","src":"Hindi","ety":"S. धामन्, rt. धा; or ध्यामन्","pos":"s.f.","def":"s.f. Equality (of age or size); measure, size","pg":505,"subs":[["dāʼīṅ-dār = dāʼīṅ-kā","adj. & s.m. (f. -ī), Of equal age or size; — an equal (in age or size).",0]],"chain":[["Sanskrit","धामन्"]],"fq":0},{"u":"دين","d":"दैन","r":"dain","src":"Sanskrit","ety":"fr. दिन","pos":"adj.","def":"adj. Relating to a day, diurnal, daily.","pg":558,"fq":0},{"u":"دين","d":"दैन","r":"dain","src":"Sanskrit","ety":"fr. दीन","pos":"s.m.","def":"s.m. Poverty, wretchedness, misery, miserable condition; humbleness, lowliness; meanness; covetousness.","pg":558,"fq":0},{"u":"ڐين","d":"डैन","r":"ḍain","src":"Hindi","ety":"S. डयन 'flying'","pos":"s.m.","def":"s.m. Wing (of a bird).","pg":576,"chain":[["Sanskrit","डयन"]],"fq":0},{"u":"دين","d":"","r":"dain, den","src":"Arabic","ety":"","pos":"s.m.","def":"s.m. A debt; a loan (syn. qarẓ)","pg":558,"subs":[["dain-tamassukī","s.f. The certificate given to a banker who has given up his effects",0],["dain-dār","s.m. A debtor, ower (of, -kā)",0],["daīn-ě-muʼajjal","s.m. A debt payable on demand",0],["dain-ě-muwajjal","s.m. A debt of which payment is deferred.",0]],"syn":["qarẓ"],"fq":0},{"u":"دائين","d":"","r":"dāʼīn, dūn","src":"Hindi","ety":"","pos":"","def":"s.m. pl. (of dūn, formed after the model of the Arabic), Hill estates.","pg":505,"fq":0},{"u":"ڐينا","d":"डैना","r":"ḍainā, ḍain","src":"Hindi","ety":" = ḍain","pos":"s.m.","def":"s.m. Wing (of a bird); branch, bough (of a tree).","pg":576,"fq":0},{"u":"دائني","d":"दाइनी","r":"dāʼinī","src":"Hindi","ety":"","pos":"s.f.","def":"s.f. (prov.) = dāʼī, q.v.","pg":505,"qv":["dāʼī"],"reg":["proverbial"],"fq":0},{"u":"ڐينی","d":"डैनी","r":"ḍainī, ḍāʼin, ā, ḍainī uṅglī","src":"Hindi","ety":"from ḍāʼin, q.v.","pos":"s.f.","def":"s.f. The middle finger.","pg":576,"fq":0},{"u":"دينك","d":"दैनिक","r":"dainik","src":"Sanskrit","ety":"fr. दिन","pos":"adj.","def":"adj. Diurnal, daily ( = dain).","pg":558,"fq":0},{"u":"دينکي","d":"दैनिकी","r":"dainikī","src":"Sanskrit","ety":"","pos":"s.f.","def":"s.f. A day's hire or wages.","pg":558,"fq":0},{"u":"دينت","d":"दैंत","r":"daiṅt","src":"Hindi","ety":"","pos":"s.m.","def":"s.m. = dait, daitya, q.v.","pg":558,"qv":["daitya"],"fq":0},{"u":"دينيه","d":"दैन्य","r":"dainya","src":"Sanskrit","ety":"fr. दीन","pos":"s.m.","def":"s.m. Poverty, &c. ( = dain, and dīnatā, qq.v.).","pg":558,"fq":0},{"u":"دائر","d":"","r":"dāʼir","src":"Arabic","ety":"act. part. n. of دار (for دور","pos":"part.adj.","def":"part. adj. Going round, encircling; in process, agitated (as a law-suit); capable of being agitated; cognizable","pg":505,"subs":[["dāʼir-tajwīz","adj. Proceeding, under consideration or trial, pending",0],["dāʼir karnā","v.t. To institute (a suit), to put in (a complaint)",1],["dāʼir o sāʼir","adj. Going the circuit (judges, &c.); absolute, invested with authority.",0]],"fq":0},{"u":"دير","d":"","r":"dair","src":"Arabic","ety":"","pos":"s.m.","def":"s.m. A convent or monastery (of Christians, or of Sūfīs, &c.); a temple, a place of worship, a church.","pg":556,"fq":0},{"u":"دائره","d":"","r":"dāʼira, dāʼir","src":"Persian","ety":"for A. دائرة, fr. dāʼir, q.v.","pos":"s.m.","def":"s.m. Circuit, compass, circumference; a ring, a circle; orbit; — a large tambourin; — a monastery","pg":505,"subs":[["dāʼira-dār","s.m. The chief of a monastery, an abbot; a prior",0],["dāʼiraʼě-qut̤bī","s.m. Polar circle.",0]],"chain":[["Arabic","دائرة"]],"fq":0},{"u":"ديري","d":"","r":"dairī, dair","src":"Persian","ety":"rel. n. fr. A. dair","pos":"adj.","def":"adj. Of or appertaining to an idol temple, &c. (see dair).","pg":557,"chain":[["Arabic","dair"]],"fq":0},{"u":"ديتن","d":"दैतन","r":"daitan, dait, daitya, daitan-bandheo","src":"Hindi","ety":"","pos":"s.m.","def":"s.m. 'Binder of the Daityas,' an epithet of Vishṇu.","pg":555,"fq":0},{"u":"ديتيه","d":"दैतेय","r":"daiteya, diti","src":"Sanskrit","ety":"fr. diti","pos":"s.m.","def":"s.m. A son of Diti, &c. ( = daitya, q.v.); — adj. Proceeding from or belonging to the Daiteyas; sprung from Diti.","pg":556,"qv":["daitya"],"fq":0},{"u":"ديتيه","d":"दैत्य","r":"daitya","src":"Sanskrit","ety":"","pos":"s.m.","def":"s.m. 'A son of Diti,' a being hostile to the gods, a demon, an evil spirit, a Titan, giant (of the Hindū mythology)","pg":556,"subs":[["daitya-yug","s.m. An age of the demons (consisting of 12,000 divine years or the sum of the four Yugas or ages of man)",0],["daitya-yoni","s.m.f. The place or source of demons.",0]],"fq":2},{"u":"ديو","d":"दैव","r":"daiv, daʼīv","src":"Sanskrit","ety":"","pos":"adj.","def":"adj. (f. -ī), Of or belonging to a deity or divinity; coming from the gods, divine, celestial; — s.m. One of the forms of marriage, the gift of a daughter at a sacrifice to the officiating priest; — a deity, a celestial being; — a religious offering or rite, an oblation or offering to the gods; — divine power, destiny, fate, fortune, chance, accident; the part of the hand sacred to the gods, i.e. the tips of the fingers","pg":559,"subs":[["daiv-āgat or āgati","s.f. Providential dispensation, sudden misfortune, unforeseen disaster, accident",0],["daiva-jna","vulg. daivaggya, adj. & s.m. (f. -ā), Acquainted with fate, knowing the destinies of men, foretelling; — an astrologer, fortune-teller; a prophet",0],["daiv-jnān","vulg. daiv-gyān, s.m. Knowledge of the destinies of men, supernatural knowledge",0],["daiv-ćintā","s.f. Reliance on fate, fatalism",0],["daiv-ćintak","s.m. (f. -ikā), An astrologer; a fatalist",0],["dair-saṅyog","adj. Connected with a deity, or with fate",0],["daiv-karm","s.m. Offering oblations to the gods, sacrificing, worship of the gods, a religious rite ( = dev-karm)",0],["daiv-gati","daiv-ghaṭnā, s.f. Course of destiny, run of fate, an event for which the gods (rather than men) are answerable, fortune, lot; misfortune, accident",0],["daiv-lekhak","s.m. (f. -ikā), An astrologer, a fortune-teller",0],["daiv-vāṇī","s.f. A voice from heaven, oracle, divine revelation",0],["daivodyān","s.m. = devodyān, q.v.s.v. deva, dev",0],["daiv-yug","s.m. An age of the gods, cycle of the immortals",0],["dair-yog","s.m. A fortuitous combination, the intervention of destiny, the occurrence of any unforeseen event, fortune, chance, accident, contingency",0],["daiv-yogya","adj. Worthy of chance or fortune.",0]],"fq":1},{"u":"ديوه","d":"दैव","r":"daiva","src":"Sanskrit","ety":"","pos":"adj.","def":"adj. = daiv, q.v.","pg":561,"qv":["daiv"],"fq":0},{"u":"ديواگت","d":"दैवागत","r":"daivāgat, devāgat","src":"Hindi","ety":"S. दैव+आगति","pos":"s.f.","def":"s.f. See s.v. daiv.","pg":559,"chain":[["Sanskrit","दैव"]],"fq":0},{"u":"ديوگيه","d":"दैवज्ञ","r":"daivagya","src":"Hindi","ety":"","pos":"s.m.","def":"s.m. = daivajna, q.v.s.v. daiv.","pg":560,"qv":["daivajna"],"fq":0},{"u":"ديوجن","d":"दैवज्ञ","r":"daivajna, daivagya","src":"Sanskrit","ety":"","pos":"s.m.","def":"s.m. See s.v. daiv.","pg":560,"fq":0},{"u":"ديوك","d":"दैवक","r":"daivak","src":"Sanskrit","ety":"","pos":"s.m.","def":"s.m. (f. -ikā), An astrologer; an almanac-maker.","pg":560,"fq":0},{"u":"ديوات","d":"दैवात","r":"daivāt","src":"Sanskrit","ety":"ablat. of दैव","pos":"adv.","def":"adv. By the interposition of fate, fatally, providentially, by chance, fortuitously, accidentally.","pg":559,"fq":0},{"u":"ديوت","d":"दैवत","r":"daivat","src":"Sanskrit","ety":"","pos":"adj.","def":"adj. Of or relating to a god or to the gods, belonging to a deity; divine; s.m. A god, a deity, an idol of a god; the deities","pg":560,"subs":[["daivat-pati","s.m. 'Lord of the gods,' an epithet of Indra.",0]],"fq":0},{"u":"ديوي","d":"दैवी","r":"daivī","src":"Hindi","ety":"S. दैविका, fr. दैवः","pos":"adj.","def":"adj. Divine; wonderful (see daiv); — s.f. An inevitable accident, &c. ( = daivāgati); — adv. By chance, &c.; at length (see daivāt)","pg":561,"subs":[["daivī-gati","s.f. = daivāgati, q.v.s.v. daiv.",0]],"chain":[["Sanskrit","दैविका"]],"fq":0},{"u":"ديوکا","d":"दैविका","r":"daivikā","src":"Sanskrit","ety":"","pos":"s.f.","def":"s.f. A female astrologer; an astrologer's wife.","pg":560,"fq":0},{"u":"ديويه","d":"दैवीय","r":"daivīya","src":"Sanskrit","ety":"","pos":"adj.","def":"adj. Of or relating to the gods or to fate.","pg":561,"fq":0},{"u":"ديويه","d":"दैव्य","r":"daivya","src":"Sanskrit","ety":"","pos":"s.m.","def":"s.m. Divine power or effect, fate, fortune, chance.","pg":561,"fq":0},{"u":"ديا","d":"दैया","r":"daiyā","src":"Hindi","ety":"Prk. दत्तिओ; S. दात्रिका","pos":"s.f.","def":"s.f. Mother; — the stand that children run to in playing hide and seek","pg":555,"subs":[["daiyā-dahāṛ or dhāṛ","s.f. 'A cry for mother'; a cry for help; a loud noise, outcry.",0]],"chain":[["Prakrit","दत्तिओ"],["Sanskrit","दात्रिका"]],"fq":0},{"u":"داعيه","d":"","r":"dāʻiya, dāʻiyat","src":"Persian","ety":"for A. داعية dāʻiyat, fem., v.n. fr دعو","pos":"s.m.","def":"s.m. Claim, pretention; demand; suit, petition, plaint, complaint; desire, wish.","pg":501,"chain":[["Arabic","داعية"]],"fq":0},{"u":"ديڙ","d":"दैयड़","r":"daiyar","src":"Hindi","ety":"","pos":"s.m.","def":"s.m. = daheṛ, q.v.","pg":557,"qv":["daheṛ"],"fq":0},{"u":"ديت","d":"दैयत","r":"daiyat, dait","src":"Hindi","ety":"","pos":"s.m.","def":"s.m. = ديتيه daitya, q.v.","pg":555,"qv":["daitya"],"fq":0},{"u":"ديوث","d":"","r":"daiyūs̤","src":"Arabic","ety":"fr. ديث 'to be soft, or easy'","pos":"s.m.","def":"s.m. A wittol, a tame cuckold; one who winks at the adultery of his wife or the fornication of his female relations from interested motives.","pg":560,"root":"د ي ث","fq":0},{"u":"ديوس","d":"","r":"daiyūs","src":"Arabic","ety":"","pos":"s.m.","def":"s.m. = daiyūs̤, q.v.","pg":560,"qv":["daiyūs̤"],"fq":0},{"u":"داج","d":"","r":"dāj","src":"Arabic","ety":"v.n. fr. دجو 'to cover'","pos":"s.m.","def":"s.m. A dark night; darkness, obscurity.","pg":499,"root":"د ج و","fq":0},{"u":"دجال","d":"","r":"dajjāl","src":"Arabic","ety":"fr. دجل 'to conceal the truth'","pos":"s.m.","def":"s.m. A liar, a great deceiver; — the false Christ, Antichrist; — adj. & s.m. Having one eye; — a one-eyed man.","pg":507,"root":"د ج ل","fq":0},{"u":"داك","d":"दाक","r":"dāk","src":"Hindi","ety":"","pos":"s.f.","def":"s.f. = dākh, q.v.","pg":501,"qv":["dākh"],"fq":2},{"u":"دق","d":"","r":"daq","src":"Persian","ety":"prob. fr. A. دقّ","pos":"s.m.","def":"s.m. Woollen cloth from which hairs hang, a coarse kind of woollen cloth (such as that of which a faqīr's blanket is made); — a fine and precious sort of cloth.","pg":519,"chain":[["Arabic","دقّ"]],"fq":2},{"u":"ڐاك","d":"डाक","r":"ḍāk","src":"Hindi","ety":"prob. fr. S. द्राक् 'quickly,' or v.n. of ḍāknā, q.v.","pos":"s.f.","def":"s.f. Post (for conveyance of letters), the mail; disposition or relay of horses, or runners, or pālkī-bearers along a road (for conveyance of the post or travellers); travelling by post; a post-office","pg":562,"subs":[["ḍāk biṭhānā","(-kī) = ḍāk lagānā, q.v.",1],["ḍāk-bahangī","s.f. Parcel-post",0],["ḍāk-piyāda","s.m. = ḍāk-wālā, q.v.",0],["ḍāk-ćaukī","s.f. A post station, a station or stage at which a relay (of horses, or runners, &c.) is posted (for conveyance of the mail, or travellers)",0],["ḍāk-ḵẖāna","s.m. Post-office",0],["ḍāk-kā ḵẖarć","s.m. Expenses incurred in travelling by post; postal charges; postage",0],["ḍāk-kā ghoṛā","s.m. A horse used for a ḍāk or relay; (fig.) a worn-out horse; — a fast walker",0],["ḍāk-gāṛī","s.f. Mail-cart; mail-train; a carriage used in travelling by ḍāk",0],["ḍāk-ghar","s.m. Post-office",0],["ḍāk lagānā","(-kī), To post relays (of horses, or runners, or pālkī-bearers)",1],["ḍāk lagnā","v.n. A post to be organized; a ḍāk or relay (of horses, &c.) to be laid",1],["ḍāk-maḥśūl","s.m. Postal charges, postage",0],["ḍāk-meṅ ćiṭṭhī ḍālnā or lagānā","To post a letter",1],["ḍāk-wālā","s.m. Postman; letter carrier, runner",0],["ḍāk-o-ḍāk","adv. In the manner of the post, postingly, post-haste, without stopping on the way.",0]],"chain":[["Sanskrit","द्राक्"]],"fq":2},{"u":"ڐاك","d":"डाक","r":"ḍāk","src":"Hindi","ety":"prob. S. दाहकः; rt. दह्; cf. ḍahnā","pos":"s.m.","def":"s.m. A piece of gold or silver leaf, &c. placed under a gem (in a ring) to heighten its brilliance, a foil; a coloured substance placed under glass to form a mock gem ( = ḍāṅk).","pg":562,"chain":[["Sanskrit","दाहकः"]],"fq":2},{"u":"ڐاك","d":"डाक","r":"ḍāk","src":"Hindi","ety":"Prk. डक्किओ; S. दंष्ट्री+कः","pos":"s.m.","def":"s.m. The husband of a ḍākinī, q.v.; a wizard, sorcerer.","pg":562,"qv":["ḍākinī"],"chain":[["Prakrit","डक्किओ"],["Sanskrit","दंष्ट्री"]],"fq":2},{"u":"ڐك","d":"डक","r":"ḍak","src":"Hindi","ety":"","pos":"s.m.","def":"s.m. = ḍaṅk, q.v.","pg":565,"qv":["ḍaṅk"],"fq":2},{"u":"داك","d":"दाक","r":"dāk, dā","src":"Sanskrit","ety":"rt. dā, 'to give","pos":"s.m.","def":"s.m. Giver, donor, one who makes presents (esp. to Brāhmans); the institutor of a sacrifice who employs and pays the officiating priests.","pg":501,"fq":2},{"u":"ڐاك","d":"डाक","r":"ḍāk, ḍāk-nā","src":"Hindi","ety":"fr. ḍāk-nā, q.v.","pos":"s.f.","def":"s.f. Continual vomiting; — calling out, shouting, &c.; bidding (at an auction)","pg":562,"subs":[["ḍāk bolnā","To bid (at an auction)",1],["ḍāk-nīlām","s.m. Auction-sale.",0]],"fq":2},{"u":"ڐاکا","d":"डाका","r":"ḍākā","src":"Hindi","ety":"Prk. डक्कओ or डक्कअं; S. दष्ट+कः or कं","pos":"s.m.","def":"s.m. Robbery, gang-robbery; an attack by a band of robbers; a band or gang of robbers","pg":562,"subs":[["ḍākā paṛnā","v.n. An attack to be made by robbers or 'dacoits,' 'dacoits' to fall (upon)",1],["ḍākā ḍenā","ḍākā ḍālnā, To commit 'dacoity' or robbery in gangs",0],["ḍākā-zanī","s.f. 'Dacoity,' highway-robbery ( = ḍakaitī).",0]],"chain":[["Prakrit","डक्कओ"],["Sanskrit","दष्ट"]],"fq":1},{"u":"دقائِق","d":"","r":"daqāʼiq, daqīqa, daqīq","src":"Arabic","ety":"","pos":"","def":"s.m. pl. (of daqīqa), Subtleties, nice points; difficulties; minutiæ; minutes, moments; — flour, meal (in this sense used in P. for the A. sing. daqīq).","pg":520,"fq":0},{"u":"ڐاکيت","d":"डाकैत","r":"ḍākait","src":"Hindi","ety":"","pos":"s.m.","def":"s.m. = ḍakait, q.v.","pg":562,"qv":["ḍakait"],"fq":0},{"u":"ڐکيت","d":"डकैत","r":"ḍakait","src":"Hindi","ety":"ḍākā, q.v.+ait = āʼit = Prk. आइत्तो = आयंतो = आवेंतो = S. आपयन्, the term. of the pres. part. with the caus. aug. āpi","pos":"s.m.","def":"s.m. One of a gang of robbers, a 'dacoit,' robber, brigand, highwayman, pirate ( = ḍākū).","pg":565,"chain":[["Prakrit","आइत्तो"],["Sanskrit","आपयन्"]],"fq":0},{"u":"ڐاکيتي","d":"डाकैती","r":"ḍākaitī","src":"Hindi","ety":"","pos":"s.f.","def":"s.f. = ḍakaitī, q.v.","pg":562,"qv":["ḍakaitī"],"fq":0},{"u":"ڐکيتي","d":"डकैती","r":"ḍakaitī","src":"Hindi","ety":"the preceding+ī = Prk. इआ = S. इका","pos":"s.f.","def":"s.f. Gang-robbery, 'dacoity,' highway-robbery, robbery, piracy.","pg":565,"chain":[["Prakrit","इआ"],["Sanskrit","इका"]],"fq":0},{"u":"دکاکين","d":"","r":"dakākīn, dukkān","src":"Arabic","ety":"","pos":"","def":"s.f. pl. (of dukkān), Shops.","pg":520,"fq":0},{"u":"ڐکار","d":"डकार","r":"ḍakār, ḍakārnā","src":"Hindi","ety":"fr. ḍakārnā, q.v.","pos":"s.f.","def":"s.f. A belch, eructation; — roaring, roar (of a tiger, &c.); bellowing, lowing (of an ox)","pg":565,"subs":[["ḍakār lenā","To belch",1],["dakār na-lenā","'Not to belch,' to make no noise, give or make no sign, to keep one's own counsel, not to betray oneself.",1]],"fq":0},{"u":"ڐاکر","d":"डाकर","r":"ḍākar, ḍākrā","src":"Hindi","ety":"Prk. डक्कडी and क्कडडओ; S. दष्ट+र, and र +कः","pos":"","def":"A strong, rich, clayey soil (regarded as the best, or second best, quality of soil; but requiring much ram to saturate it sufficiently for sowing).","pg":562,"chain":[["Prakrit","डक्कडी"],["Sanskrit","दष्ट"]],"fq":0},{"u":"ڐکارنا","d":"डकारना","r":"ḍakārnā","src":"Hindi","ety":"ḍakār˚ = S. उद्गार, rt. गृ with उद्","pos":"v.n.","def":"v.n. 'To belch'; to roar, bellow, low, make a loud noise; — v.t. To take down with a noise, to gulp down, to swallow; to embezzle","pg":565,"subs":[["ḍakār-baiṭhnā","ḍakār-jānā (with acc.), To swallow up; to embezzle, make away with, misappropriate.",0]],"chain":[["Sanskrit","उद्गार"]],"fq":1},{"u":"ڐکوت","d":"डकौत","r":"ḍakaut, ḍakautiyā","src":"Hindi","ety":"prob. S. दक्ष+पुत्रः and पुत्र+इकः","pos":"s.m.","def":"s.m. A caste of Hindūs descended from a Brāhmin on the father's and a gwālin on the mother's side (they subsist on alms asked on Saturdays, and are skilled in astrology and fortune-telling, &c.); an individual of this caste.","pg":565,"chain":[["Sanskrit","दक्ष"]],"fq":0},{"u":"ڐکوتيا","d":"डकौतिया","r":"ḍakautiyā, ḍakaut","src":"Hindi","ety":"prob. S. दक्ष+पुत्रः and पुत्र+इकः","pos":"s.m.","def":"s.m. A caste of Hindūs descended from a Brāhmin on the father's and a gwālin on the mother's side (they subsist on alms asked on Saturdays, and are skilled in astrology and fortune-telling, &c.); an individual of this caste.","pg":565,"chain":[["Sanskrit","दक्ष"]],"fq":0},{"u":"ڐکڐکاکر","d":"डकडकाकर","r":"ḍakḍakākar, ḍakḍakāke","src":"Hindi","ety":"past. conj. part. of next","pos":"adv.","def":"adv. With loud or large gulps, in great draughts","pg":565,"subs":[["ḍakḍakāke pīnā","v.t. To drink with loud gulps, or in large draughts.",0]],"fq":0},{"u":"ڐکڐکاکے","d":"डकडकाके","r":"ḍakḍakāke, ḍakḍakākar","src":"Hindi","ety":"past. conj. part. of next","pos":"adv.","def":"adv. With loud or large gulps, in great draughts","pg":565,"subs":[["ḍakḍakāke pīnā","v.t. To drink with loud gulps, or in large draughts.",0]],"fq":0},{"u":"ڐکڐکانا","d":"डकडकाना","r":"ḍakḍakānā","src":"Hindi","ety":"","pos":"v.n.","def":"v.n. = ḍagḍagānā, q.v.","pg":565,"qv":["ḍagḍagānā"],"fq":0},{"u":"ڐکڐکانا","d":"डकडकाना","r":"ḍakḍakānā, ḍak, ḍakār, ḍhoknā","src":"Hindi","ety":"by redupl. of ḍak; see ḍakār; and cf. ḍhoknā","pos":"v.n.","def":"v.n. To make a noise in swallowing, to take large or loud gulps; to drink great draughts.","pg":565,"fq":0},{"u":"داکهہ","d":"दाख","r":"dākh","src":"Hindi","ety":"S. द्राक्षा","pos":"s.f.","def":"s.f. Grape; a raisin","pg":501,"subs":[["dākh-ras","s.m.f. Grape-juice, wine",0],["dākh-latā","s.f. A vine: vine-tendril.",0]],"chain":[["Sanskrit","द्राक्षा"]],"fq":3},{"u":"دخ","d":"","r":"daḵẖ","src":"Persian","ety":"Zend dasha; S. daksha","pos":"adj.&s.m.","def":"adj. & s.m. Good; fit, able, qualified; — company, throng, army, row (of men); — essence (of anything).","pg":507,"chain":[["Sanskrit","daksha"]],"fq":3},{"u":"داخل","d":"","r":"dāḵẖil","src":"Arabic","ety":"act. part. n. of دخل 'to enter,' &c.","pos":"part.adj.&s.m.","def":"part. adj. & s.m. Entering, penetrating; arriving; — entered; inserted; included, comprehended; produced; forthcoming; — interior, inside; — entering (upon), taking possession (of); — entry (in a book or account); inclusion (of a minor in a larger piece of land, &c.)","pg":499,"subs":[["dāḵẖil-ḵẖārij","s.m. 'Inserting and striking out'; a transfer of land or property under one name to another name in a deed or register; erasure of an entry; — dāḵẖil-ḵẖārij karnā, To transfer land or property (by taking out the name of the former proprietor from a deed or register and inserting that of the new)",0],["dāḵẖil-dār","s.m. An occupant",0],["dāḵẖ daftar","adj. Entered upon the record, placed on record; filed with the record; laid aside, or indefinitely postponed; struck off the file",0],["dāḵẖil-daftar karnā","v.t. To file with the record, &c.",1],["dāḵẖil karnā","(-meṅ, or -ke andar), To cause to enter or be entered; to place or fix (in); to cause to arrive; to produce; to incorporate, include; to admit, lodge; to enter, insert, introduce; to enrol, enlist; to file; to deposit, to carry to credit; to pay (in); — to effect penetration",1],["dāḵẖil-karne-wālā","dāḵẖil-kunanda, s.m. One who enters or inserts, &c.; one who pays (in), payer, depositor",0],["dāḵẖil-nāma","s.m. A warrant or deed of possession; a conveyance",0],["dāḵẖil honā","(-meṅ), To enter, to come or go (in); to arrive; to penetrate; to enter (upon), take possession (of), to occupy; to come (under), to belong or appertain (to); — to be entered, be inserted, be enrolled, &c.; to be filed; to be paid (in), to be deposited.",1]],"fq":1,"sh":3128,"ipa":"/d̪ɑː.xɪl/","au":"https://upload.wikimedia.org/wikipedia/commons/transcoded/2/23/LL-Q1617_%28urd%29-%D9%86%D8%B9%D9%85_%D8%A7%D9%84%D8%A8%D8%AF%D9%84-%D8%AF%D8%A7%D8%AE%D9%90%D9%84.wav/LL-Q1617_%28urd%29-%D9%86%D8%B9%D9%85_%D8%A7%D9%84%D8%A8%D8%AF%D9%84-%D8%AF%D8%A7%D8%AE%D9%90%D9%84.wav.mp3","der":["داخل کرنا","داخل ہونا","داخلہ","داخلی"],"wety":"Borrowed from Classical Persian دَاخِل (dāxil), borrowed from Arabic دَاخِل (dāḵil)."},{"u":"دخيل","d":"","r":"daḵẖīl","src":"Arabic","ety":"v.n. fr. دخل","pos":"adj.&s.m.","def":"adj. & s.m. Allowed entrance, admitted; introduced, adopted (as a word); occupying, in possession (of land, &c.); — intimate, familiar; — meddling, interfering; — one who has entered on possession (of); — one who has a firm footing (in any business, post, or office, &c.); — an adventive abider (among a people); a guest; an intimate, a confidant; an accomplice; — one who interferes or intermeddles, a meddler","pg":508,"subs":[["daḵẖīl-kār","adj. & s.m. In possession (of lands, &c.); — an occupant; — one who has authority to interfere",0],["daḵẖīl-kārī","s.f. The being in possession (of), possession, occupation, occupancy",0],["daḵẖīl karnā","v.t. To allow (one) to enter (in, -meṅ), to admit; to put (one) in possession (of)",1],["daḵẖīl honā","(-meṅ), To enter (upon), to occupy; to be introduced or adopted (as a word); to be a meddler, to meddle, interfere (in).",1]],"root":"د خ ل","fq":1},{"u":"داخلا","d":"","r":"dāḵẖilā, dāḵẖila, dāḵẖilat, dāḵẖil","src":"Hindi","ety":"for A. داخلة dāḵẖilat, fem. of dāḵẖil","pos":"adj.&s.m.","def":"adj. & s.m. Interior, inside; — entry (in an account, &c.); insertion; quotation; entrance; entrance fee; admittance, admission; delivery or payment (of money, &c.); a receipt (for money, — esp. for revenue paid in)","pg":499,"subs":[["zāwiya-ě-dāḵẖila","s.m. (Geom.) Interior angle.",0]],"chain":[["Arabic","داخلة"]],"fq":0},{"u":"داخله","d":"","r":"dāḵẖila, dāḵẖilā, dāḵẖilat, dāḵẖil","src":"Persian","ety":"for A. داخلة dāḵẖilat, fem. of dāḵẖil","pos":"adj.&s.m.","def":"adj. & s.m. Interior, inside; — entry (in an account, &c.); insertion; quotation; entrance; entrance fee; admittance, admission; delivery or payment (of money, &c.); a receipt (for money, — esp. for revenue paid in)","pg":499,"subs":[["zāwiya-ě-dāḵẖila","s.m. (Geom.) Interior angle.",0]],"chain":[["Arabic","داخلة"]],"fq":0},{"u":"داخلي","d":"","r":"dāḵẖilī, dāḵẖil","src":"Arabic","ety":"rel. n. fr. dāḵẖil","pos":"adj.","def":"adj. Interior, internal; home (as opp. to foreign); — included, contained (in); inclusive; belonging (to); inherent","pg":499,"subs":[["dāḵẖilī mauẓaʻ","s.m. A newly formed village attached to or included in an older (aṣlī) village.",0]],"fq":0},{"u":"دکهن","d":"दखिन","r":"dakhin, dakkhin, dakhan, dakkhan","src":"Hindi","ety":"Prk. दक्खिणो; S. दक्षिणः","pos":"adj.&s.m.","def":"adj. & s.m. Southern, south; — the south; the southern part of Hindūstān, the Deccan.","pg":521,"chain":[["Prakrit","दक्खिणो"],["Sanskrit","दक्षिणः"]],"fq":0},{"u":"دکهني","d":"दखिनी","r":"dakhinī, dakkhinī, dakhanī, dakhnī","src":"Hindi","ety":"S. दक्षिणीयः; see dakkhin","pos":"adj.","def":"adj. Southern; of or belonging to southern India or the Deccan (generally applied to persons or things from the south); — dakhinī podīna, s.m. Horse-mint","pg":521,"subs":[["dakhinī ṭhairāʼo","s.m. The winter solstice",0],["dakhinī dhurā","s.m. The south pole",0],["dakhinī rās","s.m. Southern sign or constellation.",0]],"chain":[["Sanskrit","दक्षिणीयः"]],"fq":1},{"u":"دخ","d":"","r":"daḵẖḵẖ, duḵẖḵẖ","src":"Arabic","ety":"","pos":"s.m.","def":"s.m. = next, q.v.","pg":507,"qv":["next"],"fq":0},{"u":"دخل","d":"","r":"daḵẖl, daḵẖal","src":"Arabic","ety":"inf. n. of دخل 'to come in'","pos":"s.m.","def":"s.m. Entrance, ingress, admission, access; entering (upon), taking possession (of), possession, occupation, occupancy; making way or progress (in a study), progress, proficiency, knowledge; reach, grasp, scope, comprehension; possibility; capacity, competency; influence, power, authority, jurisdiction; — intrusion, interference, meddling, disturbance, molestation; — income, receipt, revenue, profit, produce, proceeds","pg":508,"subs":[["daḵẖl pānā","v.n. To have access, to be admitted; to obtain possession, be put in possession (of)",1],["daḵẖl-dār","s.m. One who has admission (to); a partner, an accomplice",0],["daḵẖl dar maʻqūlāt","Interruption, interference",0],["daḵẖl-dihānī","s.f. The giving possession (to)",0],["daḵẖl denā","(-ko), To give admission (to), to allow to enter; to interpose (in or between, -meṅ), to interfere; to interrupt, to disturb",1],["daḵẖl karnā","(-par), To enter (upon), take possession (of), to occupy; to encroach (upon); — to meddle (in, -meṅ), intermeddle, interfere (in or with), concern (oneself), intrude; to interrupt",1],["daḵẖl-karnewālā","s.m. An occupier, occupant; an encroacher, an intruder, &c.",0],["daḵẖl-meṅ rakhnā","v.t. To keep possession of, to retain",1],["daḵẖl-nāma","s.m. A document giving the right of occupancy, a writ or warrant of entrance or of possession (of lands, &c.)",0],["daḵẖl o qabẓa","s.m. Entry and possession",0],["daḵẖl-yābī","s.f. Obtaining entrance or admission; taking possession",0],["be-daḵẖl","adj. Excluded; dispossessed, ejected",0],["be-daḵẖl karnā","v.t. To exclude; to dispossess, dislodge, eject",1],["be-daḵẖlī","s.f. Dispossession, ejectment.",0]],"fq":1,"sh":3091},{"u":"دخمه","d":"","r":"daḵẖma, dakhma","src":"Persian","ety":"Zend dakhma","pos":"s.m.","def":"s.m. The house for the reception of the dead among the Gabrs or fire-worshippers; a vault or tomb for the dead; a coffin; — a substance like lights which a male camel protrudes from the mouth when in heat.","pg":508,"fq":0},{"u":"دکهنائي","d":"दखनाई","r":"dakhnāʼī","src":"Hindi","ety":"˚ī = Prk. इआ = S. इका","pos":"s.f.","def":"s.f. A south wind ( = dakhnā).","pg":521,"chain":[["Prakrit","इआ"],["Sanskrit","इका"]],"fq":0},{"u":"ڐاکی","d":"डाकी","r":"ḍākī","src":"Hindi","ety":"Prk. डक्किओ; S. दंष्ट्री+कः","pos":"adj.&s.m.","def":"adj. & s.m. Gluttonous, voracious; — a glutton.","pg":562,"chain":[["Prakrit","डक्किओ"],["Sanskrit","दंष्ट्री"]],"fq":0},{"u":"دقيق","d":"","r":"daqīq","src":"Arabic","ety":"v.n. fr. دق 'to be slender,' &c.","pos":"adj.","def":"adj. Slender, small, minute, fine, thin (opp. to g̠alīz̤); paltry, trifling, inconsiderable; subtile, nice, abstruse, recondite, obscure, difficult; — s.m. Flour, meal; farina.","pg":520,"root":"د ق","fq":1},{"u":"دقيقه","d":"","r":"daqīqa, daqīqat, daqīq","src":"Persian","ety":"for A. دقيقة daqīqat, fem. of daqīq","pos":"s.m.","def":"s.m. Anything small or minute, a particle; an inconsiderable or trifling business or matter; a subtile question, abstruse or nice point; — a minute, a moment of time","pg":520,"subs":[["daqīqa-ras","adj. Comprehending nice or abstruse points, penetrating, discerning; of quick apprehension.",0]],"chain":[["Arabic","دقيقة"]],"fq":0},{"u":"ڐاکن","d":"डाकिन","r":"ḍākin","src":"Hindi","ety":"fem. of ḍākiya; -in = Prk. इणी = S. इनी","pos":"s.f.","def":"s.f. A female robber; the wife of a 'dacoit' or robber; — a postman's wife.","pg":562,"chain":[["Prakrit","इणी"],["Sanskrit","इनी"]],"fq":0},{"u":"ڐاکن","d":"डाकिन","r":"ḍākin","src":"Hindi","ety":"","pos":"s.f.","def":"s.f. = ḍākinī, q.v.","pg":562,"qv":["ḍākinī"],"fq":0},{"u":"ڐاکني","d":"डाकिनी","r":"ḍākinī","src":"Hindi","ety":"Prk. डक्किणी, डाकिणी; S. डाकिनी, दंष्ट्रिणी","pos":"s.f.","def":"s.f. A kind of female demon, a female imp, a witch whose evil eye causes children to pine and die (and who is believed to consume their livers); — (met.) a termagant, a shrew.","pg":562,"reg":["metaphorical"],"chain":[["Prakrit","डक्किणी"],["Sanskrit","डाकिनी"]],"fq":1},{"u":"ڐاکيا","d":"डाकिया","r":"ḍākiyā","src":"Hindi","ety":"ḍāk, 'the post'+Prk. इओ = S. इकः (इन्+कः)","pos":"s.m.","def":"s.m. Postman ( = ḍāk-wālā, q.v.).","pg":562,"qv":["ḍāk-wālā"],"chain":[["Prakrit","इओ"],["Sanskrit","इकः"]],"fq":0},{"u":"ڐاکيا","d":"डाकिया","r":"ḍākiyā, ḍākī","src":"Hindi","ety":"i.q. ḍākī","pos":"s.m.","def":"s.m. = ḍākū, q.v.","pg":562,"qv":["ḍākū"],"fq":0},{"u":"دقاق","d":"","r":"daqqāk","src":"Arabic","ety":"v.n. fr. دقّ 'to break,' &c.","pos":"s.m.","def":"s.m. One who bruises, brays, or pounds; a corn-grinder.","pg":520,"root":"د ق ق","fq":0},{"u":"دکهنا","d":"दक्खिना","r":"dakkhinā, dakhnā","src":"Hindi","ety":"Prk. दक्खिणओ and दक्खिणा; S. दक्षिण+कः and दक्षिणा","pos":"s.f.","def":"s.f. Southern; — a southerly wind.","pg":521,"chain":[["Prakrit","दक्खिणओ"],["Sanskrit","दक्षिण"]],"fq":0},{"u":"دکهناين","d":"दक्खिनायन","r":"dakkhināyan, dakhanāyan","src":"Hindi","ety":"","pos":"s.m.","def":"s.m. = dakshiṇāyan, q.v.s.v. dakshiṇ","pg":521,"subs":[["dakkhināyan-sūraj","s.m. = dakkhināyan.",0]],"qv":["dakshiṇāyan"],"fq":0},{"u":"ڐاکنا","d":"डाकना","r":"ḍāknā","src":"Hindi","ety":"ḍāk˚ = S. उद्+वम्+कृ; cf. ḍoknā, ḍoṅknā","pos":"v.n.","def":"v.n. To vomit; — to call out, bawl, shout, vociferate, roar, bellow (cf. ḍakārnā, and daḍūknā).","pg":562,"chain":[["Sanskrit","उद्"]],"fq":0},{"u":"دق ولق","d":"","r":"daq-o-laq, dak-o-lak, dag̠-o-lag̠, laq-o-daq","src":"Persian","ety":"prob. A. دكّ and لق; also written dak-o-lak, dag̠-o-lag̠, laq-o-daq, &c.","pos":"s.m.","def":"s.m. An extensive uncultivated plain; a desert.","pg":520,"chain":[["Arabic","دكّ"]],"fq":0},{"u":"ڐکوري","d":"डकोरी","r":"ḍakorī","src":"Hindi","ety":"ḍak or ḍaṅk, q.v.+Prk. उल्लिआ = S. उल+इका","pos":"s.f.","def":"s.f. (dialec.), A wasp; a hornet.","pg":565,"reg":["dialectal"],"chain":[["Prakrit","उल्लिआ"],["Sanskrit","उल"]],"fq":0},{"u":"ڐکرا","d":"डकरा","r":"ḍakrā","src":"Hindi","ety":"prob. fr. S. दंश;+rā = Prk. अडओ = S. र+कः","pos":"s.m.","def":"s.m. Venom, poison; a kind of medicament or drug.","pg":565,"chain":[["Sanskrit","दंश"],["Prakrit","अडओ"],["Sanskrit","र"]],"fq":0},{"u":"ڐاکرا","d":"डाकरा","r":"ḍākrā, ḍākar","src":"Hindi","ety":"Prk. डक्कडी and क्कडडओ; S. दष्ट+र, and र +कः","pos":"","def":"A strong, rich, clayey soil (regarded as the best, or second best, quality of soil; but requiring much ram to saturate it sufficiently for sowing).","pg":562,"chain":[["Prakrit","डक्कडी"],["Sanskrit","दष्ट"]],"fq":0},{"u":"ڐکرانا","d":"डकराना","r":"ḍakrānā, ḍakārnā","src":"Hindi","ety":" = ḍakārnā, q.v.","pos":"v.n.","def":"v.n. To make a loud noise, to roar, bellow, low (as an ox); to cry aloud or bitterly.","pg":565,"fq":0},{"u":"دکش","d":"दक्ष","r":"daksha, daksh","src":"Sanskrit","ety":"","pos":"adj.&s.m.","def":"adj. & s.m. Able, competent, fit, suitable; dexterous, deft, expert, adroit, skilful, clever; — an able, or clever, or dexterous person; a scholar, panḍit; — name of one of the Prajāpatis, sons of Brahmā","pg":520,"subs":[["dakśhādhvara-dhwaṅsa-kr̤it","(˚ksha+adh˚), s.m. 'Disturber of the sacrifice of Daksha'; an epithet of Śiva (Daksha having instituted a sacrifice to which he invited all the gods except his son-in-law Śiva and his wife Satī, the latter went unbid, and being received contemptuously, threw herself into the fire; upon which an emanation or incarnation of Śiva was produced named Vīra-bhadra, who attacked Daksha, and a general affray ensued: Daksha was decapitated, but was restored to life by Śiva at the prayer of the gods)",0],["daksha-prajāpati","s.m. = daksh (see prajā-pati)",0],["daksha-jā","s.f. = daksha-kanyā, q.v.",0],["daksha-sut","s.m. 'Son of Daksh,' ( = praćetas)",0],["daksha-sutā","and daksha-kanyā, s.f. 'Daughter of Daksha,' Durgā (called also Pārvatī, Devī, Satī, &c.).",0]],"fq":2},{"u":"داکش","d":"दाक्ष","r":"dāksha, dāksh, daksha","src":"Sanskrit","ety":"fr. daksha","pos":"adj.","def":"adj. Relating or appertaining to Daksha.","pg":501,"fq":2},{"u":"دکشتا","d":"दक्षता","r":"dakshatā, dakshatva","src":"Sanskrit","ety":"","pos":"","def":"s.f. = S دکشتو दक्षत्व dakshatva, s.m. Ability, cleverness, dexterity.","pg":520,"fq":0},{"u":"دکشتو","d":"दक्षत्व","r":"dakshatva, dakshatā","src":"Sanskrit","ety":"","pos":"","def":"s.m. = S دکشتا दक्षता dakshatā, s.f. Ability, cleverness, dexterity.","pg":520,"fq":0},{"u":"داکشايني","d":"दाक्षायिणी","r":"dākshāyiṇī","src":"Sanskrit","ety":"","pos":"s.f.","def":"s.f. Any of the daughters of Daksha; — name of the nymph and asterism Rohiṇī; — the plant Croton polyandrum; — f. pl. The twenty-seven lunar mansions (considered mythologically as the daughters of Daksha and wives of the moon).","pg":501,"fq":0},{"u":"داکشي","d":"दाक्षि","r":"dākshi","src":"Sanskrit","ety":"","pos":"s.m.","def":"s.m. Son of Daksha","pg":501,"subs":[["dākshi-kanṭhā","s.f. Name of a village in the north of India in the country of the Vāhlikas or Balḵẖ",0],["dākshi-kanṭhīya","adj. & s.m. Relating to Dākshi-kanṭhā; produced or born in Dākshi-kanṭhā; — a native of Dākshi-kanṭhā.",0]],"fq":0},{"u":"دکشي","d":"दक्षी","r":"dakshī","src":"Hindi","ety":"S. दक्ष+इकः (इन्+कः)","pos":"adj.","def":"adj. Able, fit, competent, well-qualified ( = daksh, q.v.).","pg":520,"qv":["daksh"],"chain":[["Sanskrit","दक्ष"]],"fq":0},{"u":"دکشنا","d":"दक्षिणा","r":"dakshiṇā","src":"Persian","ety":"","pos":"s.f.","def":"s.f. The south ( = dakshiṇ, q.v.); — fee for spiritual services, a present to Brāhmans on occasions of sacrifice; donation, reward, alms (esp. to Brāhmans); — a figure of the goddess Durgā in which the right side is said to be advanced.","pg":520,"qv":["dakshiṇ"],"fq":0},{"u":"دکشن","d":"दक्षिण","r":"dakshiṇa, dakshiṇ","src":"Sanskrit","ety":"","pos":"adj.&s.m.","def":"adj. & s.m. (f. -ā), Right (opp. of left; see dahinā); southern, south; — able, competent, clever, skilful, dexterous, deft; — straightforward, candid, sincere, upright, honest; polite, affable, amiable, pleasing; — the right hand or side; the south; the southern part of Hindūstān","pg":520,"subs":[["dakshiṇ-akshāṅśa","s.m. Southern latitude",0],["dakshiṇāćār","(˚ṇa+āć˚), adj. & s.m. Honest or upright in conduct; — one who conducts himself honestly",0],["dakshiṇāćal","(˚ṇa+ać˚), s.m. The Malaya mountain",0],["dakshiṇ-āgni","(˚ṇa+ag˚), s.m. The southern fire of the altar, a sacred fire placed towards the south",0],["dakshiṇā-mukh","dakshiṇ-mukh, adj. & adv. Having the face turned southward, facing the south; — s.m. One who turns his face towards the south",0],["dakshiṇāyan","(˚ṇa+ay˚), s.m. The sun's progress south of the equator, southing, south-declination, the half-year in which the sun moves from north to south, the winter solstice",0],["dakshiṇāyana-sūrya","s.m. = dakshiṇāyan, q.v.",0],["dakshiṇāvart","(˚nā+āv˚), adj. & s.m. Turning towards the right; turning to the south; — the south country, the Dakkhan; — a conch shell with the valve opening to the right",0],["dakshiṇ-paśćim","s.m. The south-west quarter",0],["dakshiṇ-pūrvā","s.f. The south-east quarter",0],["dakshiṇ-diśā","s.f. The southern quarter.",0]],"fq":0,"wety":"From Sanskrit दक्षिण (dakṣiṇa), from Proto-Indo-European *deḱs-. Cognate with Lithuanian dešinė, Ancient Greek δεξιός (dexiós), Latin dexter."},{"u":"دکشنتا","d":"दक्षिणता","r":"dakshiṇatā","src":"Sanskrit","ety":"","pos":"s.f.","def":"s.f. Ability, skilfulness, cleverness, dexterity; uprightness, honesty; politeness, kindness.","pg":520,"fq":0},{"u":"دکشنين","d":"दक्षिणेन","r":"dakshiṇena, dakshiṇa","src":"Sanskrit","ety":"inst. case of dakshiṇa","pos":"adv.","def":"adv. To the right hand, on the right; to the south, southward.","pg":520,"fq":0},{"u":"دکشنی","d":"दक्षिणी","r":"dakshiṇī","src":"Hindi","ety":"S. दक्षिणीयः","pos":"adj.","def":"adj. Of or belonging to the south or the Dakkhan (a man, or horse, &c.); southern, south ( = dakhinī).","pg":520,"chain":[["Sanskrit","दक्षिणीयः"]],"fq":0},{"u":"دکشنيه","d":"दक्षिणीय","r":"dakshiṅīya, dakshiṇya","src":"Sanskrit","ety":"","pos":"adj.","def":"adj. Worthy of the sacrificial fee; meriting a reward; worthy to be honoured with presents.","pg":520,"fq":0}]